Workbook

Sheet 📋 使い方ガイド
B2: ① お金・支払い管理
B3: 収支・支払・請求をまとめて管理するテンプレートです
B5: 📂 シート構成
B6: シート名 | C6: 役割 | D6: 主な操作・入力
B7: ①CSVペースト | C7: 銀行・カードのCSVデータを貼る場所 | D7: 日付・摘要・金額（出金はマイナス）・科目を貼り付け or 入力
B8: ②収支管理 | C8: 科目×月のマトリクスで収支を自動集計 | D8: ①の入力が完了すると自動更新。科目・月別グラフも自動生成
B9: ③取引先マスタ | C9: 定期的な支払先を登録しておく場所 | D9: 取引先名・支払サイクル・標準金額・科目を入力
B10: ④支払管理 | C10: 月締めの支払一覧。取引先を選ぶだけで金額が入る | D10: 取引先名を選択→科目・金額が自動参照。済フラグで色分け管理
B11: ⑤請求書作成 | C11: 印刷・PDF出力用の請求書フォーム | D11: 品目・数量・単価を入力→金額・合計・税額が自動計算。A4縦で印刷可
B12: ⑥入金確認 | C12: 発行した請求書の入金状況を管理 | D12: 請求書番号・請求先・金額・期限を入力。入金日を記録して差額を確認
B15: 🔗 データの流れ（シート間のつながり）
B16: 入力元シート | C16: 参照先シート | D16: つながりの内容
B17: ①CSVペースト | C17: ②収支管理 | D17: 科目列と日付列をもとに月別・科目別で自動集計
B18: ③取引先マスタ | C18: ④支払管理 | D18: 取引先名を選ぶと科目・標準金額を自動参照
B19: ⑤請求書作成 | C19: ⑥入金確認 | D19: 請求書発行後に請求情報を手動転記して入金状況を追跡
B22: 💡 ヒント：青字のセルは自動計算セルです。直接入力すると数式が消えるためご注意ください。
B23: 💡 ヒント：グレーの行と白の行が交互になっています。行を追加する場合は最終行の下に追加してください。

Sheet ①CSVペースト
A1: ① CSVペースト ― 銀行・カードのCSVデータをここに貼り付けてください
A2: ※ 金額は入金をプラス・出金をマイナスで1列に入力してください 例）入金 +150,000 / 出金 -45,000 科目を選ぶと②収支管理に自動集計されます
A3: 日付 | B3: 摘要（取引内容） | C3: 金額（円）※出金はマイナス | D3: 残高（円） | E3: 科目 | F3: 備考
A4: 46174 | B4: 〇〇銀行 振込入金 | C4: 150000 | D4: 500000 | E4: 売上
A5: 46176 | B5: △△カード 引落し | C5: -45000 | D5: 455000 | E5: 消耗品費 | F5: 事務用品
A6: 46183 | B6: 家賃 自動引落し | C6: -80000 | D6: 375000 | E6: 地代家賃

Sheet ②収支管理
B1: ② 収支管理 ― 科目別・月別の集計表
B2: ※ ①CSVペーストシートの「科目」列と「日付」列を正確に入力すると自動集計されます
B4: 科 目 | C4: 1月 | D4: 2月 | E4: 3月 | F4: 4月 | G4: 5月 | H4: 6月 | I4: 7月 | J4: 8月 | K4: 9月 | L4: 10月 | M4: 11月 | N4: 12月 | O4: 年間合計
B5: 【収 入】
B6: 売上 | C6: =SUMPRODUCT((ISNUMBER(①CSVペースト!$A$4:$A$103))*(MONTH(IF(ISNUMBER(①CSVペースト!$A$4:$A$103),①CSVペースト!$A$4:$A$103,TODAY()))=1)*(①CSVペースト!$E$4:$E$103="売上")*(①CSVペースト!$C$4:$C$103)) -> 0 | D6: =SUMPRODUCT((ISNUMBER(①CSVペースト!$A$4:$A$103))*(MONTH(IF(ISNUMBER(①CSVペースト!$A$4:$A$103),①CSVペースト!$A$4:$A$103,TODAY()))=2)*(①CSVペースト!$E$4:$E$103="売上")*(①CSVペースト!$C$4:$C$103)) -> 0 | E6: =SUMPRODUCT((ISNUMBER(①CSVペースト!$A$4:$A$103))*(MONTH(IF(ISNUMBER(①CSVペースト!$A$4:$A$103),①CSVペースト!$A$4:$A$103,TODAY()))=3)*(①CSVペースト!$E$4:$E$103="売上")*(①CSVペースト!$C$4:$C$103)) -> 0 | F6: =SUMPRODUCT((ISNUMBER(①CSVペースト!$A$4:$A$103))*(MONTH(IF(ISNUMBER(①CSVペースト!$A$4:$A$103),①CSVペースト!$A$4:$A$103,TODAY()))=4)*(①CSVペースト!$E$4:$E$103="売上")*(①CSVペースト!$C$4:$C$103)) -> 0 | G6: =SUMPRODUCT((ISNUMBER(①CSVペースト!$A$4:$A$103))*(MONTH(IF(ISNUMBER(①CSVペースト!$A$4:$A$103),①CSVペースト!$A$4:$A$103,TODAY()))=5)*(①CSVペースト!$E$4:$E$103="売上")*(①CSVペースト!$C$4:$C$103)) -> 0 | H6: =SUMPRODUCT((ISNUMBER(①CSVペースト!$A$4:$A$103))*(MONTH(IF(ISNUMBER(①CSVペースト!$A$4:$A$103),①CSVペースト!$A$4:$A$103,TODAY()))=6)*(①CSVペースト!$E$4:$E$103="売上")*(①CSVペースト!$C$4:$C$103)) -> 150000 | I6: =SUMPRODUCT((ISNUMBER(①CSVペースト!$A$4:$A$103))*(MONTH(IF(ISNUMBER(①CSVペースト!$A$4:$A$103),①CSVペースト!$A$4:$A$103,TODAY()))=7)*(①CSVペースト!$E$4:$E$103="売上")*(①CSVペースト!$C$4:$C$103)) -> 0 | J6: =SUMPRODUCT((ISNUMBER(①CSVペースト!$A$4:$A$103))*(MONTH(IF(ISNUMBER(①CSVペースト!$A$4:$A$103),①CSVペースト!$A$4:$A$103,TODAY()))=8)*(①CSVペースト!$E$4:$E$103="売上")*(①CSVペースト!$C$4:$C$103)) -> 0 | K6: =SUMPRODUCT((ISNUMBER(①CSVペースト!$A$4:$A$103))*(MONTH(IF(ISNUMBER(①CSVペースト!$A$4:$A$103),①CSVペースト!$A$4:$A$103,TODAY()))=9)*(①CSVペースト!$E$4:$E$103="売上")*(①CSVペースト!$C$4:$C$103)) -> 0 | L6: =SUMPRODUCT((ISNUMBER(①CSVペースト!$A$4:$A$103))*(MONTH(IF(ISNUMBER(①CSVペースト!$A$4:$A$103),①CSVペースト!$A$4:$A$103,TODAY()))=10)*(①CSVペースト!$E$4:$E$103="売上")*(①CSVペースト!$C$4:$C$103)) -> 0 | M6: =SUMPRODUCT((ISNUMBER(①CSVペースト!$A$4:$A$103))*(MONTH(IF(ISNUMBER(①CSVペースト!$A$4:$A$103),①CSVペースト!$A$4:$A$103,TODAY()))=11)*(①CSVペースト!$E$4:$E$103="売上")*(①CSVペースト!$C$4:$C$103)) -> 0 | N6: =SUMPRODUCT((ISNUMBER(①CSVペースト!$A$4:$A$103))*(MONTH(IF(ISNUMBER(①CSVペースト!$A$4:$A$103),①CSVペースト!$A$4:$A$103,TODAY()))=12)*(①CSVペースト!$E$4:$E$103="売上")*(①CSVペースト!$C$4:$C$103)) -> 0 | O6: =SUM(C6:N6) -> 150000
B7: その他収入 | C7: =SUMPRODUCT((ISNUMBER(①CSVペースト!$A$4:$A$103))*(MONTH(IF(ISNUMBER(①CSVペースト!$A$4:$A$103),①CSVペースト!$A$4:$A$103,TODAY()))=1)*(①CSVペースト!$E$4:$E$103="その他収入")*(①CSVペースト!$C$4:$C$103)) -> 0 | D7: =SUMPRODUCT((ISNUMBER(①CSVペースト!$A$4:$A$103))*(MONTH(IF(ISNUMBER(①CSVペースト!$A$4:$A$103),①CSVペースト!$A$4:$A$103,TODAY()))=2)*(①CSVペースト!$E$4:$E$103="その他収入")*(①CSVペースト!$C$4:$C$103)) -> 0 | E7: =SUMPRODUCT((ISNUMBER(①CSVペースト!$A$4:$A$103))*(MONTH(IF(ISNUMBER(①CSVペースト!$A$4:$A$103),①CSVペースト!$A$4:$A$103,TODAY()))=3)*(①CSVペースト!$E$4:$E$103="その他収入")*(①CSVペースト!$C$4:$C$103)) -> 0 | F7: =SUMPRODUCT((ISNUMBER(①CSVペースト!$A$4:$A$103))*(MONTH(IF(ISNUMBER(①CSVペースト!$A$4:$A$103),①CSVペースト!$A$4:$A$103,TODAY()))=4)*(①CSVペースト!$E$4:$E$103="その他収入")*(①CSVペースト!$C$4:$C$103)) -> 0 | G7: =SUMPRODUCT((ISNUMBER(①CSVペースト!$A$4:$A$103))*(MONTH(IF(ISNUMBER(①CSVペースト!$A$4:$A$103),①CSVペースト!$A$4:$A$103,TODAY()))=5)*(①CSVペースト!$E$4:$E$103="その他収入")*(①CSVペースト!$C$4:$C$103)) -> 0 | H7: =SUMPRODUCT((ISNUMBER(①CSVペースト!$A$4:$A$103))*(MONTH(IF(ISNUMBER(①CSVペースト!$A$4:$A$103),①CSVペースト!$A$4:$A$103,TODAY()))=6)*(①CSVペースト!$E$4:$E$103="その他収入")*(①CSVペースト!$C$4:$C$103)) -> 0 | I7: =SUMPRODUCT((ISNUMBER(①CSVペースト!$A$4:$A$103))*(MONTH(IF(ISNUMBER(①CSVペースト!$A$4:$A$103),①CSVペースト!$A$4:$A$103,TODAY()))=7)*(①CSVペースト!$E$4:$E$103="その他収入")*(①CSVペースト!$C$4:$C$103)) -> 0 | J7: =SUMPRODUCT((ISNUMBER(①CSVペースト!$A$4:$A$103))*(MONTH(IF(ISNUMBER(①CSVペースト!$A$4:$A$103),①CSVペースト!$A$4:$A$103,TODAY()))=8)*(①CSVペースト!$E$4:$E$103="その他収入")*(①CSVペースト!$C$4:$C$103)) -> 0 | K7: =SUMPRODUCT((ISNUMBER(①CSVペースト!$A$4:$A$103))*(MONTH(IF(ISNUMBER(①CSVペースト!$A$4:$A$103),①CSVペースト!$A$4:$A$103,TODAY()))=9)*(①CSVペースト!$E$4:$E$103="その他収入")*(①CSVペースト!$C$4:$C$103)) -> 0 | L7: =SUMPRODUCT((ISNUMBER(①CSVペースト!$A$4:$A$103))*(MONTH(IF(ISNUMBER(①CSVペースト!$A$4:$A$103),①CSVペースト!$A$4:$A$103,TODAY()))=10)*(①CSVペースト!$E$4:$E$103="その他収入")*(①CSVペースト!$C$4:$C$103)) -> 0 | M7: =SUMPRODUCT((ISNUMBER(①CSVペースト!$A$4:$A$103))*(MONTH(IF(ISNUMBER(①CSVペースト!$A$4:$A$103),①CSVペースト!$A$4:$A$103,TODAY()))=11)*(①CSVペースト!$E$4:$E$103="その他収入")*(①CSVペースト!$C$4:$C$103)) -> 0 | N7: =SUMPRODUCT((ISNUMBER(①CSVペースト!$A$4:$A$103))*(MONTH(IF(ISNUMBER(①CSVペースト!$A$4:$A$103),①CSVペースト!$A$4:$A$103,TODAY()))=12)*(①CSVペースト!$E$4:$E$103="その他収入")*(①CSVペースト!$C$4:$C$103)) -> 0 | O7: =SUM(C7:N7) -> 0
B8: 収入合計 | C8: =SUM(C6:C7) -> 0 | D8: =SUM(D6:D7) -> 0 | E8: =SUM(E6:E7) -> 0 | F8: =SUM(F6:F7) -> 0 | G8: =SUM(G6:G7) -> 0 | H8: =SUM(H6:H7) -> 150000 | I8: =SUM(I6:I7) -> 0 | J8: =SUM(J6:J7) -> 0 | ... O8: =SUM(O6:O7) -> 150000
B10: 【支 出】
B11: 仕入 | C11: =SUMPRODUCT((ISNUMBER(①CSVペースト!$A$4:$A$103))*(MONTH(IF(ISNUMBER(①CSVペースト!$A$4:$A$103),①CSVペースト!$A$4:$A$103,TODAY()))=1)*(①CSVペースト!$E$4:$E$103="仕入")*ABS(①CSVペースト!$C$4:$C$103)) -> 0 | D11: =SUMPRODUCT((ISNUMBER(①CSVペースト!$A$4:$A$103))*(MONTH(IF(ISNUMBER(①CSVペースト!$A$4:$A$103),①CSVペースト!$A$4:$A$103,TODAY()))=2)*(①CSVペースト!$E$4:$E$103="仕入")*ABS(①CSVペースト!$C$4:$C$103)) -> 0 | E11: =SUMPRODUCT((ISNUMBER(①CSVペースト!$A$4:$A$103))*(MONTH(IF(ISNUMBER(①CSVペースト!$A$4:$A$103),①CSVペースト!$A$4:$A$103,TODAY()))=3)*(①CSVペースト!$E$4:$E$103="仕入")*ABS(①CSVペースト!$C$4:$C$103)) -> 0 | F11: =SUMPRODUCT((ISNUMBER(①CSVペースト!$A$4:$A$103))*(MONTH(IF(ISNUMBER(①CSVペースト!$A$4:$A$103),①CSVペースト!$A$4:$A$103,TODAY()))=4)*(①CSVペースト!$E$4:$E$103="仕入")*ABS(①CSVペースト!$C$4:$C$103)) -> 0 | G11: =SUMPRODUCT((ISNUMBER(①CSVペースト!$A$4:$A$103))*(MONTH(IF(ISNUMBER(①CSVペースト!$A$4:$A$103),①CSVペースト!$A$4:$A$103,TODAY()))=5)*(①CSVペースト!$E$4:$E$103="仕入")*ABS(①CSVペースト!$C$4:$C$103)) -> 0 | H11: =SUMPRODUCT((ISNUMBER(①CSVペースト!$A$4:$A$103))*(MONTH(IF(ISNUMBER(①CSVペースト!$A$4:$A$103),①CSVペースト!$A$4:$A$103,TODAY()))=6)*(①CSVペースト!$E$4:$E$103="仕入")*ABS(①CSVペースト!$C$4:$C$103)) -> 0 | I11: =SUMPRODUCT((ISNUMBER(①CSVペースト!$A$4:$A$103))*(MONTH(IF(ISNUMBER(①CSVペースト!$A$4:$A$103),①CSVペースト!$A$4:$A$103,TODAY()))=7)*(①CSVペースト!$E$4:$E$103="仕入")*ABS(①CSVペースト!$C$4:$C$103)) -> 0 | J11: =SUMPRODUCT((ISNUMBER(①CSVペースト!$A$4:$A$103))*(MONTH(IF(ISNUMBER(①CSVペースト!$A$4:$A$103),①CSVペースト!$A$4:$A$103,TODAY()))=8)*(①CSVペースト!$E$4:$E$103="仕入")*ABS(①CSVペースト!$C$4:$C$103)) -> 0 | K11: =SUMPRODUCT((ISNUMBER(①CSVペースト!$A$4:$A$103))*(MONTH(IF(ISNUMBER(①CSVペースト!$A$4:$A$103),①CSVペースト!$A$4:$A$103,TODAY()))=9)*(①CSVペースト!$E$4:$E$103="仕入")*ABS(①CSVペースト!$C$4:$C$103)) -> 0 | L11: =SUMPRODUCT((ISNUMBER(①CSVペースト!$A$4:$A$103))*(MONTH(IF(ISNUMBER(①CSVペースト!$A$4:$A$103),①CSVペースト!$A$4:$A$103,TODAY()))=10)*(①CSVペースト!$E$4:$E$103="仕入")*ABS(①CSVペースト!$C$4:$C$103)) -> 0 | M11: =SUMPRODUCT((ISNUMBER(①CSVペースト!$A$4:$A$103))*(MONTH(IF(ISNUMBER(①CSVペースト!$A$4:$A$103),①CSVペースト!$A$4:$A$103,TODAY()))=11)*(①CSVペースト!$E$4:$E$103="仕入")*ABS(①CSVペースト!$C$4:$C$103)) -> 0 | N11: =SUMPRODUCT((ISNUMBER(①CSVペースト!$A$4:$A$103))*(MONTH(IF(ISNUMBER(①CSVペースト!$A$4:$A$103),①CSVペースト!$A$4:$A$103,TODAY()))=12)*(①CSVペースト!$E$4:$E$103="仕入")*ABS(①CSVペースト!$C$4:$C$103)) -> 0 | O11: =SUM(C11:N11) -> 0
B12: 交通費 | C12: =SUMPRODUCT((ISNUMBER(①CSVペースト!$A$4:$A$103))*(MONTH(IF(ISNUMBER(①CSVペースト!$A$4:$A$103),①CSVペースト!$A$4:$A$103,TODAY()))=1)*(①CSVペースト!$E$4:$E$103="交通費")*ABS(①CSVペースト!$C$4:$C$103)) -> 0 | D12: =SUMPRODUCT((ISNUMBER(①CSVペースト!$A$4:$A$103))*(MONTH(IF(ISNUMBER(①CSVペースト!$A$4:$A$103),①CSVペースト!$A$4:$A$103,TODAY()))=2)*(①CSVペースト!$E$4:$E$103="交通費")*ABS(①CSVペースト!$C$4:$C$103)) -> 0 | E12: =SUMPRODUCT((ISNUMBER(①CSVペースト!$A$4:$A$103))*(MONTH(IF(ISNUMBER(①CSVペースト!$A$4:$A$103),①CSVペースト!$A$4:$A$103,TODAY()))=3)*(①CSVペースト!$E$4:$E$103="交通費")*ABS(①CSVペースト!$C$4:$C$103)) -> 0 | F12: =SUMPRODUCT((ISNUMBER(①CSVペースト!$A$4:$A$103))*(MONTH(IF(ISNUMBER(①CSVペースト!$A$4:$A$103),①CSVペースト!$A$4:$A$103,TODAY()))=4)*(①CSVペースト!$E$4:$E$103="交通費")*ABS(①CSVペースト!$C$4:$C$103)) -> 0 | G12: =SUMPRODUCT((ISNUMBER(①CSVペースト!$A$4:$A$103))*(MONTH(IF(ISNUMBER(①CSVペースト!$A$4:$A$103),①CSVペースト!$A$4:$A$103,TODAY()))=5)*(①CSVペースト!$E$4:$E$103="交通費")*ABS(①CSVペースト!$C$4:$C$103)) -> 0 | H12: =SUMPRODUCT((ISNUMBER(①CSVペースト!$A$4:$A$103))*(MONTH(IF(ISNUMBER(①CSVペースト!$A$4:$A$103),①CSVペースト!$A$4:$A$103,TODAY()))=6)*(①CSVペースト!$E$4:$E$103="交通費")*ABS(①CSVペースト!$C$4:$C$103)) -> 0 | I12: =SUMPRODUCT((ISNUMBER(①CSVペースト!$A$4:$A$103))*(MONTH(IF(ISNUMBER(①CSVペースト!$A$4:$A$103),①CSVペースト!$A$4:$A$103,TODAY()))=7)*(①CSVペースト!$E$4:$E$103="交通費")*ABS(①CSVペースト!$C$4:$C$103)) -> 0 | J12: =SUMPRODUCT((ISNUMBER(①CSVペースト!$A$4:$A$103))*(MONTH(IF(ISNUMBER(①CSVペースト!$A$4:$A$103),①CSVペースト!$A$4:$A$103,TODAY()))=8)*(①CSVペースト!$E$4:$E$103="交通費")*ABS(①CSVペースト!$C$4:$C$103)) -> 0 | K12: =SUMPRODUCT((ISNUMBER(①CSVペースト!$A$4:$A$103))*(MONTH(IF(ISNUMBER(①CSVペースト!$A$4:$A$103),①CSVペースト!$A$4:$A$103,TODAY()))=9)*(①CSVペースト!$E$4:$E$103="交通費")*ABS(①CSVペースト!$C$4:$C$103)) -> 0 | L12: =SUMPRODUCT((ISNUMBER(①CSVペースト!$A$4:$A$103))*(MONTH(IF(ISNUMBER(①CSVペースト!$A$4:$A$103),①CSVペースト!$A$4:$A$103,TODAY()))=10)*(①CSVペースト!$E$4:$E$103="交通費")*ABS(①CSVペースト!$C$4:$C$103)) -> 0 | M12: =SUMPRODUCT((ISNUMBER(①CSVペースト!$A$4:$A$103))*(MONTH(IF(ISNUMBER(①CSVペースト!$A$4:$A$103),①CSVペースト!$A$4:$A$103,TODAY()))=11)*(①CSVペースト!$E$4:$E$103="交通費")*ABS(①CSVペースト!$C$4:$C$103)) -> 0 | N12: =SUMPRODUCT((ISNUMBER(①CSVペースト!$A$4:$A$103))*(MONTH(IF(ISNUMBER(①CSVペースト!$A$4:$A$103),①CSVペースト!$A$4:$A$103,TODAY()))=12)*(①CSVペースト!$E$4:$E$103="交通費")*ABS(①CSVペースト!$C$4:$C$103)) -> 0 | O12: =SUM(C12:N12) -> 0
B13: 通信費 | C13: =SUMPRODUCT((ISNUMBER(①CSVペースト!$A$4:$A$103))*(MONTH(IF(ISNUMBER(①CSVペースト!$A$4:$A$103),①CSVペースト!$A$4:$A$103,TODAY()))=1)*(①CSVペースト!$E$4:$E$103="通信費")*ABS(①CSVペースト!$C$4:$C$103)) -> 0 | D13: =SUMPRODUCT((ISNUMBER(①CSVペースト!$A$4:$A$103))*(MONTH(IF(ISNUMBER(①CSVペースト!$A$4:$A$103),①CSVペースト!$A$4:$A$103,TODAY()))=2)*(①CSVペースト!$E$4:$E$103="通信費")*ABS(①CSVペースト!$C$4:$C$103)) -> 0 | E13: =SUMPRODUCT((ISNUMBER(①CSVペースト!$A$4:$A$103))*(MONTH(IF(ISNUMBER(①CSVペースト!$A$4:$A$103),①CSVペースト!$A$4:$A$103,TODAY()))=3)*(①CSVペースト!$E$4:$E$103="通信費")*ABS(①CSVペースト!$C$4:$C$103)) -> 0 | F13: =SUMPRODUCT((ISNUMBER(①CSVペースト!$A$4:$A$103))*(MONTH(IF(ISNUMBER(①CSVペースト!$A$4:$A$103),①CSVペースト!$A$4:$A$103,TODAY()))=4)*(①CSVペースト!$E$4:$E$103="通信費")*ABS(①CSVペースト!$C$4:$C$103)) -> 0 | G13: =SUMPRODUCT((ISNUMBER(①CSVペースト!$A$4:$A$103))*(MONTH(IF(ISNUMBER(①CSVペースト!$A$4:$A$103),①CSVペースト!$A$4:$A$103,TODAY()))=5)*(①CSVペースト!$E$4:$E$103="通信費")*ABS(①CSVペースト!$C$4:$C$103)) -> 0 | H13: =SUMPRODUCT((ISNUMBER(①CSVペースト!$A$4:$A$103))*(MONTH(IF(ISNUMBER(①CSVペースト!$A$4:$A$103),①CSVペースト!$A$4:$A$103,TODAY()))=6)*(①CSVペースト!$E$4:$E$103="通信費")*ABS(①CSVペースト!$C$4:$C$103)) -> 0 | I13: =SUMPRODUCT((ISNUMBER(①CSVペースト!$A$4:$A$103))*(MONTH(IF(ISNUMBER(①CSVペースト!$A$4:$A$103),①CSVペースト!$A$4:$A$103,TODAY()))=7)*(①CSVペースト!$E$4:$E$103="通信費")*ABS(①CSVペースト!$C$4:$C$103)) -> 0 | J13: =SUMPRODUCT((ISNUMBER(①CSVペースト!$A$4:$A$103))*(MONTH(IF(ISNUMBER(①CSVペースト!$A$4:$A$103),①CSVペースト!$A$4:$A$103,TODAY()))=8)*(①CSVペースト!$E$4:$E$103="通信費")*ABS(①CSVペースト!$C$4:$C$103)) -> 0 | K13: =SUMPRODUCT((ISNUMBER(①CSVペースト!$A$4:$A$103))*(MONTH(IF(ISNUMBER(①CSVペースト!$A$4:$A$103),①CSVペースト!$A$4:$A$103,TODAY()))=9)*(①CSVペースト!$E$4:$E$103="通信費")*ABS(①CSVペースト!$C$4:$C$103)) -> 0 | L13: =SUMPRODUCT((ISNUMBER(①CSVペースト!$A$4:$A$103))*(MONTH(IF(ISNUMBER(①CSVペースト!$A$4:$A$103),①CSVペースト!$A$4:$A$103,TODAY()))=10)*(①CSVペースト!$E$4:$E$103="通信費")*ABS(①CSVペースト!$C$4:$C$103)) -> 0 | M13: =SUMPRODUCT((ISNUMBER(①CSVペースト!$A$4:$A$103))*(MONTH(IF(ISNUMBER(①CSVペースト!$A$4:$A$103),①CSVペースト!$A$4:$A$103,TODAY()))=11)*(①CSVペースト!$E$4:$E$103="通信費")*ABS(①CSVペースト!$C$4:$C$103)) -> 0 | N13: =SUMPRODUCT((ISNUMBER(①CSVペースト!$A$4:$A$103))*(MONTH(IF(ISNUMBER(①CSVペースト!$A$4:$A$103),①CSVペースト!$A$4:$A$103,TODAY()))=12)*(①CSVペースト!$E$4:$E$103="通信費")*ABS(①CSVペースト!$C$4:$C$103)) -> 0 | O13: =SUM(C13:N13) -> 0
B14: 消耗品費 | C14: =SUMPRODUCT((ISNUMBER(①CSVペースト!$A$4:$A$103))*(MONTH(IF(ISNUMBER(①CSVペースト!$A$4:$A$103),①CSVペースト!$A$4:$A$103,TODAY()))=1)*(①CSVペースト!$E$4:$E$103="消耗品費")*ABS(①CSVペースト!$C$4:$C$103)) -> 0 | D14: =SUMPRODUCT((ISNUMBER(①CSVペースト!$A$4:$A$103))*(MONTH(IF(ISNUMBER(①CSVペースト!$A$4:$A$103),①CSVペースト!$A$4:$A$103,TODAY()))=2)*(①CSVペースト!$E$4:$E$103="消耗品費")*ABS(①CSVペースト!$C$4:$C$103)) -> 0 | E14: =SUMPRODUCT((ISNUMBER(①CSVペースト!$A$4:$A$103))*(MONTH(IF(ISNUMBER(①CSVペースト!$A$4:$A$103),①CSVペースト!$A$4:$A$103,TODAY()))=3)*(①CSVペースト!$E$4:$E$103="消耗品費")*ABS(①CSVペースト!$C$4:$C$103)) -> 0 | F14: =SUMPRODUCT((ISNUMBER(①CSVペースト!$A$4:$A$103))*(MONTH(IF(ISNUMBER(①CSVペースト!$A$4:$A$103),①CSVペースト!$A$4:$A$103,TODAY()))=4)*(①CSVペースト!$E$4:$E$103="消耗品費")*ABS(①CSVペースト!$C$4:$C$103)) -> 0 | G14: =SUMPRODUCT((ISNUMBER(①CSVペースト!$A$4:$A$103))*(MONTH(IF(ISNUMBER(①CSVペースト!$A$4:$A$103),①CSVペースト!$A$4:$A$103,TODAY()))=5)*(①CSVペースト!$E$4:$E$103="消耗品費")*ABS(①CSVペースト!$C$4:$C$103)) -> 45000 | H14: =SUMPRODUCT((ISNUMBER(①CSVペースト!$A$4:$A$103))*(MONTH(IF(ISNUMBER(①CSVペースト!$A$4:$A$103),①CSVペースト!$A$4:$A$103,TODAY()))=6)*(①CSVペースト!$E$4:$E$103="消耗品費")*ABS(①CSVペースト!$C$4:$C$103)) -> 0 | I14: =SUMPRODUCT((ISNUMBER(①CSVペースト!$A$4:$A$103))*(MONTH(IF(ISNUMBER(①CSVペースト!$A$4:$A$103),①CSVペースト!$A$4:$A$103,TODAY()))=7)*(①CSVペースト!$E$4:$E$103="消耗品費")*ABS(①CSVペースト!$C$4:$C$103)) -> 0 | J14: =SUMPRODUCT((ISNUMBER(①CSVペースト!$A$4:$A$103))*(MONTH(IF(ISNUMBER(①CSVペースト!$A$4:$A$103),①CSVペースト!$A$4:$A$103,TODAY()))=8)*(①CSVペースト!$E$4:$E$103="消耗品費")*ABS(①CSVペースト!$C$4:$C$103)) -> 0 | K14: =SUMPRODUCT((ISNUMBER(①CSVペースト!$A$4:$A$103))*(MONTH(IF(ISNUMBER(①CSVペースト!$A$4:$A$103),①CSVペースト!$A$4:$A$103,TODAY()))=9)*(①CSVペースト!$E$4:$E$103="消耗品費")*ABS(①CSVペースト!$C$4:$C$103)) -> 0 | L14: =SUMPRODUCT((ISNUMBER(①CSVペースト!$A$4:$A$103))*(MONTH(IF(ISNUMBER(①CSVペースト!$A$4:$A$103),①CSVペースト!$A$4:$A$103,TODAY()))=10)*(①CSVペースト!$E$4:$E$103="消耗品費")*ABS(①CSVペースト!$C$4:$C$103)) -> 0 | M14: =SUMPRODUCT((ISNUMBER(①CSVペースト!$A$4:$A$103))*(MONTH(IF(ISNUMBER(①CSVペースト!$A$4:$A$103),①CSVペースト!$A$4:$A$103,TODAY()))=11)*(①CSVペースト!$E$4:$E$103="消耗品費")*ABS(①CSVペースト!$C$4:$C$103)) -> 0 | N14: =SUMPRODUCT((ISNUMBER(①CSVペースト!$A$4:$A$103))*(MONTH(IF(ISNUMBER(①CSVペースト!$A$4:$A$103),①CSVペースト!$A$4:$A$103,TODAY()))=12)*(①CSVペースト!$E$4:$E$103="消耗品費")*ABS(①CSVペースト!$C$4:$C$103)) -> 0 | O14: =SUM(C14:N14) -> 45000
B15: 外注費 | C15: =SUMPRODUCT((ISNUMBER(①CSVペースト!$A$4:$A$103))*(MONTH(IF(ISNUMBER(①CSVペースト!$A$4:$A$103),①CSVペースト!$A$4:$A$103,TODAY()))=1)*(①CSVペースト!$E$4:$E$103="外注費")*ABS(①CSVペースト!$C$4:$C$103)) -> 0 | D15: =SUMPRODUCT((ISNUMBER(①CSVペースト!$A$4:$A$103))*(MONTH(IF(ISNUMBER(①CSVペースト!$A$4:$A$103),①CSVペースト!$A$4:$A$103,TODAY()))=2)*(①CSVペースト!$E$4:$E$103="外注費")*ABS(①CSVペースト!$C$4:$C$103)) -> 0 | E15: =SUMPRODUCT((ISNUMBER(①CSVペースト!$A$4:$A$103))*(MONTH(IF(ISNUMBER(①CSVペースト!$A$4:$A$103),①CSVペースト!$A$4:$A$103,TODAY()))=3)*(①CSVペースト!$E$4:$E$103="外注費")*ABS(①CSVペースト!$C$4:$C$103)) -> 0 | F15: =SUMPRODUCT((ISNUMBER(①CSVペースト!$A$4:$A$103))*(MONTH(IF(ISNUMBER(①CSVペースト!$A$4:$A$103),①CSVペースト!$A$4:$A$103,TODAY()))=4)*(①CSVペースト!$E$4:$E$103="外注費")*ABS(①CSVペースト!$C$4:$C$103)) -> 0 | G15: =SUMPRODUCT((ISNUMBER(①CSVペースト!$A$4:$A$103))*(MONTH(IF(ISNUMBER(①CSVペースト!$A$4:$A$103),①CSVペースト!$A$4:$A$103,TODAY()))=5)*(①CSVペースト!$E$4:$E$103="外注費")*ABS(①CSVペースト!$C$4:$C$103)) -> 0 | H15: =SUMPRODUCT((ISNUMBER(①CSVペースト!$A$4:$A$103))*(MONTH(IF(ISNUMBER(①CSVペースト!$A$4:$A$103),①CSVペースト!$A$4:$A$103,TODAY()))=6)*(①CSVペースト!$E$4:$E$103="外注費")*ABS(①CSVペースト!$C$4:$C$103)) -> 0 | I15: =SUMPRODUCT((ISNUMBER(①CSVペースト!$A$4:$A$103))*(MONTH(IF(ISNUMBER(①CSVペースト!$A$4:$A$103),①CSVペースト!$A$4:$A$103,TODAY()))=7)*(①CSVペースト!$E$4:$E$103="外注費")*ABS(①CSVペースト!$C$4:$C$103)) -> 0 | J15: =SUMPRODUCT((ISNUMBER(①CSVペースト!$A$4:$A$103))*(MONTH(IF(ISNUMBER(①CSVペースト!$A$4:$A$103),①CSVペースト!$A$4:$A$103,TODAY()))=8)*(①CSVペースト!$E$4:$E$103="外注費")*ABS(①CSVペースト!$C$4:$C$103)) -> 0 | K15: =SUMPRODUCT((ISNUMBER(①CSVペースト!$A$4:$A$103))*(MONTH(IF(ISNUMBER(①CSVペースト!$A$4:$A$103),①CSVペースト!$A$4:$A$103,TODAY()))=9)*(①CSVペースト!$E$4:$E$103="外注費")*ABS(①CSVペースト!$C$4:$C$103)) -> 0 | L15: =SUMPRODUCT((ISNUMBER(①CSVペースト!$A$4:$A$103))*(MONTH(IF(ISNUMBER(①CSVペースト!$A$4:$A$103),①CSVペースト!$A$4:$A$103,TODAY()))=10)*(①CSVペースト!$E$4:$E$103="外注費")*ABS(①CSVペースト!$C$4:$C$103)) -> 0 | M15: =SUMPRODUCT((ISNUMBER(①CSVペースト!$A$4:$A$103))*(MONTH(IF(ISNUMBER(①CSVペースト!$A$4:$A$103),①CSVペースト!$A$4:$A$103,TODAY()))=11)*(①CSVペースト!$E$4:$E$103="外注費")*ABS(①CSVペースト!$C$4:$C$103)) -> 0 | N15: =SUMPRODUCT((ISNUMBER(①CSVペースト!$A$4:$A$103))*(MONTH(IF(ISNUMBER(①CSVペースト!$A$4:$A$103),①CSVペースト!$A$4:$A$103,TODAY()))=12)*(①CSVペースト!$E$4:$E$103="外注費")*ABS(①CSVペースト!$C$4:$C$103)) -> 0 | O15: =SUM(C15:N15) -> 0
B16: 地代家賃 | C16: =SUMPRODUCT((ISNUMBER(①CSVペースト!$A$4:$A$103))*(MONTH(IF(ISNUMBER(①CSVペースト!$A$4:$A$103),①CSVペースト!$A$4:$A$103,TODAY()))=1)*(①CSVペースト!$E$4:$E$103="地代家賃")*ABS(①CSVペースト!$C$4:$C$103)) -> 0 | D16: =SUMPRODUCT((ISNUMBER(①CSVペースト!$A$4:$A$103))*(MONTH(IF(ISNUMBER(①CSVペースト!$A$4:$A$103),①CSVペースト!$A$4:$A$103,TODAY()))=2)*(①CSVペースト!$E$4:$E$103="地代家賃")*ABS(①CSVペースト!$C$4:$C$103)) -> 0 | E16: =SUMPRODUCT((ISNUMBER(①CSVペースト!$A$4:$A$103))*(MONTH(IF(ISNUMBER(①CSVペースト!$A$4:$A$103),①CSVペースト!$A$4:$A$103,TODAY()))=3)*(①CSVペースト!$E$4:$E$103="地代家賃")*ABS(①CSVペースト!$C$4:$C$103)) -> 0 | F16: =SUMPRODUCT((ISNUMBER(①CSVペースト!$A$4:$A$103))*(MONTH(IF(ISNUMBER(①CSVペースト!$A$4:$A$103),①CSVペースト!$A$4:$A$103,TODAY()))=4)*(①CSVペースト!$E$4:$E$103="地代家賃")*ABS(①CSVペースト!$C$4:$C$103)) -> 0 | G16: =SUMPRODUCT((ISNUMBER(①CSVペースト!$A$4:$A$103))*(MONTH(IF(ISNUMBER(①CSVペースト!$A$4:$A$103),①CSVペースト!$A$4:$A$103,TODAY()))=5)*(①CSVペースト!$E$4:$E$103="地代家賃")*ABS(①CSVペースト!$C$4:$C$103)) -> 80000 | H16: =SUMPRODUCT((ISNUMBER(①CSVペースト!$A$4:$A$103))*(MONTH(IF(ISNUMBER(①CSVペースト!$A$4:$A$103),①CSVペースト!$A$4:$A$103,TODAY()))=6)*(①CSVペースト!$E$4:$E$103="地代家賃")*ABS(①CSVペースト!$C$4:$C$103)) -> 0 | I16: =SUMPRODUCT((ISNUMBER(①CSVペースト!$A$4:$A$103))*(MONTH(IF(ISNUMBER(①CSVペースト!$A$4:$A$103),①CSVペースト!$A$4:$A$103,TODAY()))=7)*(①CSVペースト!$E$4:$E$103="地代家賃")*ABS(①CSVペースト!$C$4:$C$103)) -> 0 | J16: =SUMPRODUCT((ISNUMBER(①CSVペースト!$A$4:$A$103))*(MONTH(IF(ISNUMBER(①CSVペースト!$A$4:$A$103),①CSVペースト!$A$4:$A$103,TODAY()))=8)*(①CSVペースト!$E$4:$E$103="地代家賃")*ABS(①CSVペースト!$C$4:$C$103)) -> 0 | K16: =SUMPRODUCT((ISNUMBER(①CSVペースト!$A$4:$A$103))*(MONTH(IF(ISNUMBER(①CSVペースト!$A$4:$A$103),①CSVペースト!$A$4:$A$103,TODAY()))=9)*(①CSVペースト!$E$4:$E$103="地代家賃")*ABS(①CSVペースト!$C$4:$C$103)) -> 0 | L16: =SUMPRODUCT((ISNUMBER(①CSVペースト!$A$4:$A$103))*(MONTH(IF(ISNUMBER(①CSVペースト!$A$4:$A$103),①CSVペースト!$A$4:$A$103,TODAY()))=10)*(①CSVペースト!$E$4:$E$103="地代家賃")*ABS(①CSVペースト!$C$4:$C$103)) -> 0 | M16: =SUMPRODUCT((ISNUMBER(①CSVペースト!$A$4:$A$103))*(MONTH(IF(ISNUMBER(①CSVペースト!$A$4:$A$103),①CSVペースト!$A$4:$A$103,TODAY()))=11)*(①CSVペースト!$E$4:$E$103="地代家賃")*ABS(①CSVペースト!$C$4:$C$103)) -> 0 | N16: =SUMPRODUCT((ISNUMBER(①CSVペースト!$A$4:$A$103))*(MONTH(IF(ISNUMBER(①CSVペースト!$A$4:$A$103),①CSVペースト!$A$4:$A$103,TODAY()))=12)*(①CSVペースト!$E$4:$E$103="地代家賃")*ABS(①CSVペースト!$C$4:$C$103)) -> 0 | O16: =SUM(C16:N16) -> 80000
B17: 広告宣伝費 | C17: =SUMPRODUCT((ISNUMBER(①CSVペースト!$A$4:$A$103))*(MONTH(IF(ISNUMBER(①CSVペースト!$A$4:$A$103),①CSVペースト!$A$4:$A$103,TODAY()))=1)*(①CSVペースト!$E$4:$E$103="広告宣伝費")*ABS(①CSVペースト!$C$4:$C$103)) -> 0 | D17: =SUMPRODUCT((ISNUMBER(①CSVペースト!$A$4:$A$103))*(MONTH(IF(ISNUMBER(①CSVペースト!$A$4:$A$103),①CSVペースト!$A$4:$A$103,TODAY()))=2)*(①CSVペースト!$E$4:$E$103="広告宣伝費")*ABS(①CSVペースト!$C$4:$C$103)) -> 0 | E17: =SUMPRODUCT((ISNUMBER(①CSVペースト!$A$4:$A$103))*(MONTH(IF(ISNUMBER(①CSVペースト!$A$4:$A$103),①CSVペースト!$A$4:$A$103,TODAY()))=3)*(①CSVペースト!$E$4:$E$103="広告宣伝費")*ABS(①CSVペースト!$C$4:$C$103)) -> 0 | F17: =SUMPRODUCT((ISNUMBER(①CSVペースト!$A$4:$A$103))*(MONTH(IF(ISNUMBER(①CSVペースト!$A$4:$A$103),①CSVペースト!$A$4:$A$103,TODAY()))=4)*(①CSVペースト!$E$4:$E$103="広告宣伝費")*ABS(①CSVペースト!$C$4:$C$103)) -> 0 | G17: =SUMPRODUCT((ISNUMBER(①CSVペースト!$A$4:$A$103))*(MONTH(IF(ISNUMBER(①CSVペースト!$A$4:$A$103),①CSVペースト!$A$4:$A$103,TODAY()))=5)*(①CSVペースト!$E$4:$E$103="広告宣伝費")*ABS(①CSVペースト!$C$4:$C$103)) -> 0 | H17: =SUMPRODUCT((ISNUMBER(①CSVペースト!$A$4:$A$103))*(MONTH(IF(ISNUMBER(①CSVペースト!$A$4:$A$103),①CSVペースト!$A$4:$A$103,TODAY()))=6)*(①CSVペースト!$E$4:$E$103="広告宣伝費")*ABS(①CSVペースト!$C$4:$C$103)) -> 0 | I17: =SUMPRODUCT((ISNUMBER(①CSVペースト!$A$4:$A$103))*(MONTH(IF(ISNUMBER(①CSVペースト!$A$4:$A$103),①CSVペースト!$A$4:$A$103,TODAY()))=7)*(①CSVペースト!$E$4:$E$103="広告宣伝費")*ABS(①CSVペースト!$C$4:$C$103)) -> 0 | J17: =SUMPRODUCT((ISNUMBER(①CSVペースト!$A$4:$A$103))*(MONTH(IF(ISNUMBER(①CSVペースト!$A$4:$A$103),①CSVペースト!$A$4:$A$103,TODAY()))=8)*(①CSVペースト!$E$4:$E$103="広告宣伝費")*ABS(①CSVペースト!$C$4:$C$103)) -> 0 | K17: =SUMPRODUCT((ISNUMBER(①CSVペースト!$A$4:$A$103))*(MONTH(IF(ISNUMBER(①CSVペースト!$A$4:$A$103),①CSVペースト!$A$4:$A$103,TODAY()))=9)*(①CSVペースト!$E$4:$E$103="広告宣伝費")*ABS(①CSVペースト!$C$4:$C$103)) -> 0 | L17: =SUMPRODUCT((ISNUMBER(①CSVペースト!$A$4:$A$103))*(MONTH(IF(ISNUMBER(①CSVペースト!$A$4:$A$103),①CSVペースト!$A$4:$A$103,TODAY()))=10)*(①CSVペースト!$E$4:$E$103="広告宣伝費")*ABS(①CSVペースト!$C$4:$C$103)) -> 0 | M17: =SUMPRODUCT((ISNUMBER(①CSVペースト!$A$4:$A$103))*(MONTH(IF(ISNUMBER(①CSVペースト!$A$4:$A$103),①CSVペースト!$A$4:$A$103,TODAY()))=11)*(①CSVペースト!$E$4:$E$103="広告宣伝費")*ABS(①CSVペースト!$C$4:$C$103)) -> 0 | N17: =SUMPRODUCT((ISNUMBER(①CSVペースト!$A$4:$A$103))*(MONTH(IF(ISNUMBER(①CSVペースト!$A$4:$A$103),①CSVペースト!$A$4:$A$103,TODAY()))=12)*(①CSVペースト!$E$4:$E$103="広告宣伝費")*ABS(①CSVペースト!$C$4:$C$103)) -> 0 | O17: =SUM(C17:N17) -> 0
B18: 水道光熱費 | C18: =SUMPRODUCT((ISNUMBER(①CSVペースト!$A$4:$A$103))*(MONTH(IF(ISNUMBER(①CSVペースト!$A$4:$A$103),①CSVペースト!$A$4:$A$103,TODAY()))=1)*(①CSVペースト!$E$4:$E$103="水道光熱費")*ABS(①CSVペースト!$C$4:$C$103)) -> 0 | D18: =SUMPRODUCT((ISNUMBER(①CSVペースト!$A$4:$A$103))*(MONTH(IF(ISNUMBER(①CSVペースト!$A$4:$A$103),①CSVペースト!$A$4:$A$103,TODAY()))=2)*(①CSVペースト!$E$4:$E$103="水道光熱費")*ABS(①CSVペースト!$C$4:$C$103)) -> 0 | E18: =SUMPRODUCT((ISNUMBER(①CSVペースト!$A$4:$A$103))*(MONTH(IF(ISNUMBER(①CSVペースト!$A$4:$A$103),①CSVペースト!$A$4:$A$103,TODAY()))=3)*(①CSVペースト!$E$4:$E$103="水道光熱費")*ABS(①CSVペースト!$C$4:$C$103)) -> 0 | F18: =SUMPRODUCT((ISNUMBER(①CSVペースト!$A$4:$A$103))*(MONTH(IF(ISNUMBER(①CSVペースト!$A$4:$A$103),①CSVペースト!$A$4:$A$103,TODAY()))=4)*(①CSVペースト!$E$4:$E$103="水道光熱費")*ABS(①CSVペースト!$C$4:$C$103)) -> 0 | G18: =SUMPRODUCT((ISNUMBER(①CSVペースト!$A$4:$A$103))*(MONTH(IF(ISNUMBER(①CSVペースト!$A$4:$A$103),①CSVペースト!$A$4:$A$103,TODAY()))=5)*(①CSVペースト!$E$4:$E$103="水道光熱費")*ABS(①CSVペースト!$C$4:$C$103)) -> 0 | H18: =SUMPRODUCT((ISNUMBER(①CSVペースト!$A$4:$A$103))*(MONTH(IF(ISNUMBER(①CSVペースト!$A$4:$A$103),①CSVペースト!$A$4:$A$103,TODAY()))=6)*(①CSVペースト!$E$4:$E$103="水道光熱費")*ABS(①CSVペースト!$C$4:$C$103)) -> 0 | I18: =SUMPRODUCT((ISNUMBER(①CSVペースト!$A$4:$A$103))*(MONTH(IF(ISNUMBER(①CSVペースト!$A$4:$A$103),①CSVペースト!$A$4:$A$103,TODAY()))=7)*(①CSVペースト!$E$4:$E$103="水道光熱費")*ABS(①CSVペースト!$C$4:$C$103)) -> 0 | J18: =SUMPRODUCT((ISNUMBER(①CSVペースト!$A$4:$A$103))*(MONTH(IF(ISNUMBER(①CSVペースト!$A$4:$A$103),①CSVペースト!$A$4:$A$103,TODAY()))=8)*(①CSVペースト!$E$4:$E$103="水道光熱費")*ABS(①CSVペースト!$C$4:$C$103)) -> 0 | K18: =SUMPRODUCT((ISNUMBER(①CSVペースト!$A$4:$A$103))*(MONTH(IF(ISNUMBER(①CSVペースト!$A$4:$A$103),①CSVペースト!$A$4:$A$103,TODAY()))=9)*(①CSVペースト!$E$4:$E$103="水道光熱費")*ABS(①CSVペースト!$C$4:$C$103)) -> 0 | L18: =SUMPRODUCT((ISNUMBER(①CSVペースト!$A$4:$A$103))*(MONTH(IF(ISNUMBER(①CSVペースト!$A$4:$A$103),①CSVペースト!$A$4:$A$103,TODAY()))=10)*(①CSVペースト!$E$4:$E$103="水道光熱費")*ABS(①CSVペースト!$C$4:$C$103)) -> 0 | M18: =SUMPRODUCT((ISNUMBER(①CSVペースト!$A$4:$A$103))*(MONTH(IF(ISNUMBER(①CSVペースト!$A$4:$A$103),①CSVペースト!$A$4:$A$103,TODAY()))=11)*(①CSVペースト!$E$4:$E$103="水道光熱費")*ABS(①CSVペースト!$C$4:$C$103)) -> 0 | N18: =SUMPRODUCT((ISNUMBER(①CSVペースト!$A$4:$A$103))*(MONTH(IF(ISNUMBER(①CSVペースト!$A$4:$A$103),①CSVペースト!$A$4:$A$103,TODAY()))=12)*(①CSVペースト!$E$4:$E$103="水道光熱費")*ABS(①CSVペースト!$C$4:$C$103)) -> 0 | O18: =SUM(C18:N18) -> 0
B19: 雑費 | C19: =SUMPRODUCT((ISNUMBER(①CSVペースト!$A$4:$A$103))*(MONTH(IF(ISNUMBER(①CSVペースト!$A$4:$A$103),①CSVペースト!$A$4:$A$103,TODAY()))=1)*(①CSVペースト!$E$4:$E$103="雑費")*ABS(①CSVペースト!$C$4:$C$103)) -> 0 | D19: =SUMPRODUCT((ISNUMBER(①CSVペースト!$A$4:$A$103))*(MONTH(IF(ISNUMBER(①CSVペースト!$A$4:$A$103),①CSVペースト!$A$4:$A$103,TODAY()))=2)*(①CSVペースト!$E$4:$E$103="雑費")*ABS(①CSVペースト!$C$4:$C$103)) -> 0 | E19: =SUMPRODUCT((ISNUMBER(①CSVペースト!$A$4:$A$103))*(MONTH(IF(ISNUMBER(①CSVペースト!$A$4:$A$103),①CSVペースト!$A$4:$A$103,TODAY()))=3)*(①CSVペースト!$E$4:$E$103="雑費")*ABS(①CSVペースト!$C$4:$C$103)) -> 0 | F19: =SUMPRODUCT((ISNUMBER(①CSVペースト!$A$4:$A$103))*(MONTH(IF(ISNUMBER(①CSVペースト!$A$4:$A$103),①CSVペースト!$A$4:$A$103,TODAY()))=4)*(①CSVペースト!$E$4:$E$103="雑費")*ABS(①CSVペースト!$C$4:$C$103)) -> 0 | G19: =SUMPRODUCT((ISNUMBER(①CSVペースト!$A$4:$A$103))*(MONTH(IF(ISNUMBER(①CSVペースト!$A$4:$A$103),①CSVペースト!$A$4:$A$103,TODAY()))=5)*(①CSVペースト!$E$4:$E$103="雑費")*ABS(①CSVペースト!$C$4:$C$103)) -> 0 | H19: =SUMPRODUCT((ISNUMBER(①CSVペースト!$A$4:$A$103))*(MONTH(IF(ISNUMBER(①CSVペースト!$A$4:$A$103),①CSVペースト!$A$4:$A$103,TODAY()))=6)*(①CSVペースト!$E$4:$E$103="雑費")*ABS(①CSVペースト!$C$4:$C$103)) -> 0 | I19: =SUMPRODUCT((ISNUMBER(①CSVペースト!$A$4:$A$103))*(MONTH(IF(ISNUMBER(①CSVペースト!$A$4:$A$103),①CSVペースト!$A$4:$A$103,TODAY()))=7)*(①CSVペースト!$E$4:$E$103="雑費")*ABS(①CSVペースト!$C$4:$C$103)) -> 0 | J19: =SUMPRODUCT((ISNUMBER(①CSVペースト!$A$4:$A$103))*(MONTH(IF(ISNUMBER(①CSVペースト!$A$4:$A$103),①CSVペースト!$A$4:$A$103,TODAY()))=8)*(①CSVペースト!$E$4:$E$103="雑費")*ABS(①CSVペースト!$C$4:$C$103)) -> 0 | K19: =SUMPRODUCT((ISNUMBER(①CSVペースト!$A$4:$A$103))*(MONTH(IF(ISNUMBER(①CSVペースト!$A$4:$A$103),①CSVペースト!$A$4:$A$103,TODAY()))=9)*(①CSVペースト!$E$4:$E$103="雑費")*ABS(①CSVペースト!$C$4:$C$103)) -> 0 | L19: =SUMPRODUCT((ISNUMBER(①CSVペースト!$A$4:$A$103))*(MONTH(IF(ISNUMBER(①CSVペースト!$A$4:$A$103),①CSVペースト!$A$4:$A$103,TODAY()))=10)*(①CSVペースト!$E$4:$E$103="雑費")*ABS(①CSVペースト!$C$4:$C$103)) -> 0 | M19: =SUMPRODUCT((ISNUMBER(①CSVペースト!$A$4:$A$103))*(MONTH(IF(ISNUMBER(①CSVペースト!$A$4:$A$103),①CSVペースト!$A$4:$A$103,TODAY()))=11)*(①CSVペースト!$E$4:$E$103="雑費")*ABS(①CSVペースト!$C$4:$C$103)) -> 0 | N19: =SUMPRODUCT((ISNUMBER(①CSVペースト!$A$4:$A$103))*(MONTH(IF(ISNUMBER(①CSVペースト!$A$4:$A$103),①CSVペースト!$A$4:$A$103,TODAY()))=12)*(①CSVペースト!$E$4:$E$103="雑費")*ABS(①CSVペースト!$C$4:$C$103)) -> 0 | O19: =SUM(C19:N19) -> 0
B20: 支出合計 | C20: =SUM(C11:C19) -> 0 | D20: =SUM(D11:D19) -> 0 | E20: =SUM(E11:E19) -> 0 | F20: =SUM(F11:F19) -> 0 | G20: =SUM(G11:G19) -> 125000 | H20: =SUM(H11:H19) -> 0 | I20: =SUM(I11:I19) -> 0 | J20: =SUM(J11:J19) -> 0 | ... O20: =SUM(O11:O19) -> 125000
B22: 差引（収入－支出） | C22: =C8-C20 -> 0 | D22: =D8-D20 -> 0 | E22: =E8-E20 -> 0 | F22: =F8-F20 -> 0 | G22: =G8-G20 -> -125000 | H22: =H8-H20 -> 150000 | I22: =I8-I20 -> 0 | J22: =J8-J20 -> 0 | ... O22: =O8-O20 -> 25000

Sheet ③取引先マスタ
A1: ③ 取引先マスタ ― 支払先を登録しておくと④支払管理で選択できます
A3: 取引先ID | B3: 取引先名 | C3: 担当者 | D3: 連絡先 | E3: 支払サイクル | F3: 標準金額（円） | G3: 科目 | H3: 備考
A4: T001 | B4: 〇〇家主 | C4: 山田太郎 | D4: 090-XXXX-XXXX | E4: 月末払い | F4: 80000 | G4: 地代家賃
A5: T002 | B5: △△通信 | D5: 0120-XXX-XXX | E5: 月次払い | F5: 5500 | G5: 通信費
A6: T003 | B6: □□商事 | C6: 鈴木花子 | D6: 03-XXXX-XXXX | E6: 都度払い | G6: 仕入

Sheet ④支払管理
A1: ④ 支払管理（月締め） ― 取引先を選ぶと金額・科目が自動入力されます
A2: ※ 取引先名を選択すると③取引先マスタから金額・科目を自動参照します
A3: 支払月 | B3: 取引先名 | C3: 科目 | D3: 金額（円） | E3: 支払予定日 | F3: 支払済フラグ | G3: 備考
C4: =IFERROR(VLOOKUP(B4,③取引先マスタ!$B$4:$G$53,6,0),"") | D4: =IFERROR(VLOOKUP(B4,③取引先マスタ!$B$4:$F$53,5,0),"")
C5: =IFERROR(VLOOKUP(B5,③取引先マスタ!$B$4:$G$53,6,0),"") | D5: =IFERROR(VLOOKUP(B5,③取引先マスタ!$B$4:$F$53,5,0),"")
C6: =IFERROR(VLOOKUP(B6,③取引先マスタ!$B$4:$G$53,6,0),"") | D6: =IFERROR(VLOOKUP(B6,③取引先マスタ!$B$4:$F$53,5,0),"")
C7: =IFERROR(VLOOKUP(B7,③取引先マスタ!$B$4:$G$53,6,0),"") | D7: =IFERROR(VLOOKUP(B7,③取引先マスタ!$B$4:$F$53,5,0),"")
C8: =IFERROR(VLOOKUP(B8,③取引先マスタ!$B$4:$G$53,6,0),"") | D8: =IFERROR(VLOOKUP(B8,③取引先マスタ!$B$4:$F$53,5,0),"")
C9: =IFERROR(VLOOKUP(B9,③取引先マスタ!$B$4:$G$53,6,0),"") | D9: =IFERROR(VLOOKUP(B9,③取引先マスタ!$B$4:$F$53,5,0),"")
C10: =IFERROR(VLOOKUP(B10,③取引先マスタ!$B$4:$G$53,6,0),"") | D10: =IFERROR(VLOOKUP(B10,③取引先マスタ!$B$4:$F$53,5,0),"")
C11: =IFERROR(VLOOKUP(B11,③取引先マスタ!$B$4:$G$53,6,0),"") | D11: =IFERROR(VLOOKUP(B11,③取引先マスタ!$B$4:$F$53,5,0),"")
C12: =IFERROR(VLOOKUP(B12,③取引先マスタ!$B$4:$G$53,6,0),"") | D12: =IFERROR(VLOOKUP(B12,③取引先マスタ!$B$4:$F$53,5,0),"")
C13: =IFERROR(VLOOKUP(B13,③取引先マスタ!$B$4:$G$53,6,0),"") | D13: =IFERROR(VLOOKUP(B13,③取引先マスタ!$B$4:$F$53,5,0),"")
C14: =IFERROR(VLOOKUP(B14,③取引先マスタ!$B$4:$G$53,6,0),"") | D14: =IFERROR(VLOOKUP(B14,③取引先マスタ!$B$4:$F$53,5,0),"")
C15: =IFERROR(VLOOKUP(B15,③取引先マスタ!$B$4:$G$53,6,0),"") | D15: =IFERROR(VLOOKUP(B15,③取引先マスタ!$B$4:$F$53,5,0),"")
... C53: =IFERROR(VLOOKUP(B53,③取引先マスタ!$B$4:$G$53,6,0),"") | D53: =IFERROR(VLOOKUP(B53,③取引先マスタ!$B$4:$F$53,5,0),"")

Sheet ⑤請求書作成
A2: 請 求 書
A3: 請 求 先 | E3: 請求書番号 | G3: INV-001
A4: 〇〇株式会社 御中 | E4: 発 行 日
E5: 支払期限
A6: 担当： 様
A8: 下記の通りご請求申し上げます。 | E8: 【発行者情報】
A9: =IFERROR("¥ "&TEXT(SUM(F15:F22)*(1+H26),"#,##0")&" -","") -> ¥ 0 - | E9: （消費税込）
E11: 会社名・屋号
E12: 住 所
E13: 電 話 番 号
A14: 品目・内容 | C14: 摘要 | E14: 数量 | F14: 単価（円） | G14: 金額（円） | H14: 備考
G15: =IFERROR(E15*F15,"") -> 0
G16: =IFERROR(E16*F16,"") -> 0
G17: =IFERROR(E17*F17,"") -> 0
G18: =IFERROR(E18*F18,"") -> 0
G19: =IFERROR(E19*F19,"") -> 0
G20: =IFERROR(E20*F20,"") -> 0
G21: =IFERROR(E21*F21,"") -> 0
G22: =IFERROR(E22*F22,"") -> 0
F24: 小 計 | G24: =SUM(G15:G22) -> 0
F25: 消費税率 | G25: 0.1 | H25: （変更可）
F26: 消費税額 | G26: =ROUND(G24*G25,0) -> 0
F27: ご請求金額 | G27: =G24+G26 -> 0
A28: 【お振込先】
A29: 銀行名： 支店名： 口座種別： 普通 / 当座 口座番号： 名義：
A30: 【備考・注意事項】
A31: ※ 請求後は請求書番号・請求先・金額・支払期限を⑥入金確認シートに転記してください

Sheet ⑥入金確認
A1: ⑥ 入金確認 ― 請求ごとの入金状況を管理します
A3: 請求書番号 | B3: 請求先 | C3: 請求金額（円） | D3: 請求日 | E3: 支払期限 | F3: 入金日 | G3: 入金額（円） | H3: 差額（円） | I3: 状態 | J3: 備考
H4: =IFERROR(C4-G4,"") -> 0
H5: =IFERROR(C5-G5,"") -> 0
H6: =IFERROR(C6-G6,"") -> 0
H7: =IFERROR(C7-G7,"") -> 0
H8: =IFERROR(C8-G8,"") -> 0
H9: =IFERROR(C9-G9,"") -> 0
H10: =IFERROR(C10-G10,"") -> 0
H11: =IFERROR(C11-G11,"") -> 0
H12: =IFERROR(C12-G12,"") -> 0
H13: =IFERROR(C13-G13,"") -> 0
H14: =IFERROR(C14-G14,"") -> 0
H15: =IFERROR(C15-G15,"") -> 0
... H53: =IFERROR(C53-G53,"") -> 0
