Workbook

Sheet 📋 使い方ガイド
B2: ② 顧客管理
B3: 台帳型と会員型の2パターンを収録しています。不要な方は削除してご使用ください
B5: 📂 シート構成
B6: シート名 | C6: 役割 | D6: 主な操作・入力
B7: 【台帳】①顧客マスタ | C7: 顧客の基本情報を登録する台帳 | D7: 顧客IDは変更しないこと。購買記録と紐づいている
B8: 【台帳】②購買記録 | C8: 日々の売上と顧客を紐づけて記録 | D8: 顧客IDを入力すると氏名が自動表示。数量×単価で金額自動計算
B9: 【台帳】③顧客カルテ | C9: 顧客IDを入力すると基本情報と購買履歴を表示 | D9: B3セルに顧客IDを入力するだけ。累計購買金額も自動表示
B10: 【台帳】④売上分析 | C10: 月別売上グラフと顧客別売上を確認 | D10: ②購買記録の入力が完了すると自動更新
B11: 【会員】①会員マスタ | C11: 会員情報・プラン・ステータスを管理 | D11: ステータスで在籍/休会/退会を管理。退会者は自動で赤く色分け
B12: 【会員】②CSVペースト | C12: 金融機関の入金CSVデータを貼る場所 | D12: 日付・摘要（振込人名）・金額を貼り付け。③で自動照合される
B13: 【会員】③引落し管理 | C13: 会員ごとの入金状況を照合・確認 | D13: 対象月（B3）を入力すると②CSVと自動照合。状態が自動判定される
B14: 【会員】③プランマスタ | C14: プラン名と月額を登録 | D14: プラン名を登録すると①会員マスタのドロップダウンで選択可能
B15: 【会員】④売上分析 | C15: 月別会費収入とプラン別構成を確認 | D15: ③引落し管理の「済」データから自動集計。円グラフで構成比を表示
B18: 🔗 データの流れ（シート間のつながり）
B19: 入力元シート | C19: 参照先シート | D19: つながりの内容
B20: 【台帳】①顧客マスタ | C20: 【台帳】②購買記録 | D20: 顧客IDをもとに氏名を自動参照
B21: 【台帳】②購買記録 | C21: 【台帳】③顧客カルテ | D21: 顧客IDで絞り込んで購買履歴・累計金額を表示
B22: 【台帳】②購買記録 | C22: 【台帳】④売上分析 | D22: 日付と金額から月別売上を自動集計
B23: 【会員】③プランマスタ | C23: 【会員】①会員マスタ | D23: プラン名のドロップダウンと月額の自動参照
B24: 【会員】①会員マスタ | C24: 【会員】③引落し管理 | D24: 会員IDで氏名・プラン・請求金額を自動参照
B25: 【会員】②CSVペースト | C25: 【会員】③引落し管理 | D25: 摘要キーワードと対象月で入金データを自動照合
B26: 【会員】③引落し管理 | C26: 【会員】④売上分析 | D26: 「済」フラグのデータから月別会費収入を集計
B29: 💡 ヒント：青字のセルは自動計算セルです。直接入力すると数式が消えるためご注意ください。
B30: 💡 ヒント：グレーの行と白の行が交互になっています。行を追加する場合は最終行の下に追加してください。

Sheet 【台帳】①顧客マスタ
A1: 【台帳型】① 顧客マスタ ― 顧客の基本情報を登録します
A2: ※ 顧客IDは変更しないでください。購買記録シートと紐づいています。
A3: 顧客ID | B3: 台帳型と会員型の2パターンを収録しています。不要な方は削除してご使用ください | C3: フリガナ | D3: 電話番号 | E3: メールアドレス | F3: 住所 | G3: 登録日 | H3: 備考
A4: C001 | B4: 山田太郎 | C4: ヤマダタロウ | D4: 090-1234-5678 | E4: yamada@example.com | F4: 東京都渋谷区〇〇1-2-3 | G4: 46032
A5: C002 | B5: 鈴木花子 | C5: スズキハナコ | D5: 080-9876-5432 | E5: suzuki@example.com | F5: 神奈川県横浜市△△4-5-6 | G5: 46068 | H5: 常連

Sheet 【台帳】②購買記録
A1: 【台帳型】② 購買記録 ― 日々の売上と顧客を紐づけて記録します
A2: ※ 顧客IDを入力すると顧客名が自動表示されます。
A3: 記録ID | B3: 日付 | C3: 顧客ID | D3: 顧客名（自動） | E3: 商品名・サービス | F3: 数量 | G3: 単価（円） | H3: 金額（円） | I3: 担当者 | J3: 備考
A4: R001 | B4: 46174 | C4: C001 | E4: カット＋カラー | F4: 1 | G4: 15000 | H4: 15000 | I4: 田中
A5: R002 | B5: 46176 | C5: C002 | E5: カット | F5: 1 | G5: 5500 | H5: 5500 | I5: 佐藤
D6: =IFERROR(VLOOKUP(C6,【台帳】①顧客マスタ!$A$4:$B$105,2,0),"") | H6: =IFERROR(F6*G6,"") -> 0
D7: =IFERROR(VLOOKUP(C7,【台帳】①顧客マスタ!$A$4:$B$105,2,0),"") | H7: =IFERROR(F7*G7,"") -> 0
D8: =IFERROR(VLOOKUP(C8,【台帳】①顧客マスタ!$A$4:$B$105,2,0),"") | H8: =IFERROR(F8*G8,"") -> 0
D9: =IFERROR(VLOOKUP(C9,【台帳】①顧客マスタ!$A$4:$B$105,2,0),"") | H9: =IFERROR(F9*G9,"") -> 0
D10: =IFERROR(VLOOKUP(C10,【台帳】①顧客マスタ!$A$4:$B$105,2,0),"") | H10: =IFERROR(F10*G10,"") -> 0
D11: =IFERROR(VLOOKUP(C11,【台帳】①顧客マスタ!$A$4:$B$105,2,0),"") | H11: =IFERROR(F11*G11,"") -> 0
D12: =IFERROR(VLOOKUP(C12,【台帳】①顧客マスタ!$A$4:$B$105,2,0),"") | H12: =IFERROR(F12*G12,"") -> 0
D13: =IFERROR(VLOOKUP(C13,【台帳】①顧客マスタ!$A$4:$B$105,2,0),"") | H13: =IFERROR(F13*G13,"") -> 0
D14: =IFERROR(VLOOKUP(C14,【台帳】①顧客マスタ!$A$4:$B$105,2,0),"") | H14: =IFERROR(F14*G14,"") -> 0
D15: =IFERROR(VLOOKUP(C15,【台帳】①顧客マスタ!$A$4:$B$105,2,0),"") | H15: =IFERROR(F15*G15,"") -> 0
D16: =IFERROR(VLOOKUP(C16,【台帳】①顧客マスタ!$A$4:$B$105,2,0),"") | H16: =IFERROR(F16*G16,"") -> 0
D17: =IFERROR(VLOOKUP(C17,【台帳】①顧客マスタ!$A$4:$B$105,2,0),"") | H17: =IFERROR(F17*G17,"") -> 0
... D205: =IFERROR(VLOOKUP(C205,【台帳】①顧客マスタ!$A$4:$B$105,2,0),"") | H205: =IFERROR(F205*G205,"") -> 0

Sheet 【台帳】③顧客カルテ
A1: 【台帳型】③ 顧客カルテ ― 顧客IDを入力すると購買履歴が表示されます
A2: ※ B3セルに顧客IDを入力してください。
A3: 顧客ID | B3: C001
A5: 氏名 | B5: =IFERROR(VLOOKUP($B$3,【台帳】①顧客マスタ!$A$4:$H$105,2,0),"") -> 山田太郎
A6: フリガナ | B6: =IFERROR(VLOOKUP($B$3,【台帳】①顧客マスタ!$A$4:$H$105,3,0),"") -> ヤマダタロウ
A7: 電話番号 | B7: =IFERROR(VLOOKUP($B$3,【台帳】①顧客マスタ!$A$4:$H$105,4,0),"") -> 090-1234-5678
A8: メールアドレス | B8: =IFERROR(VLOOKUP($B$3,【台帳】①顧客マスタ!$A$4:$H$105,5,0),"") -> yamada@example.com
A9: 住所 | B9: =IFERROR(VLOOKUP($B$3,【台帳】①顧客マスタ!$A$4:$H$105,6,0),"") -> 東京都渋谷区〇〇1-2-3
A10: 登録日 | B10: =IFERROR(VLOOKUP($B$3,【台帳】①顧客マスタ!$A$4:$H$105,7,0),"") -> 46032
A13: 購買履歴
A14: 日付 | B14: 商品名・サービス | C14: 数量 | D14: 単価（円） | E14: 金額（円） | F14: 担当者 | G14: 備考
A15: =IFERROR("※ 購買記録シートをフィルタして顧客IDで絞り込んでください（Ctrl+Shift+L）","") -> ※ 購買記録シートをフィルタして顧客IDで絞り込んでください（Ctrl+Shift+L）
A16: 合計購買金額 | B16: =SUMIF(【台帳】②購買記録!$C$4:$C$205,$B$3,【台帳】②購買記録!$H$4:$H$205) -> 15000

Sheet 【台帳】④売上分析
A1: 【台帳型】④ 売上分析 ― 月別・顧客別の売上を自動集計します
A2: ※ ②購買記録シートに入力した内容が自動反映されます。
A4: 月別売上
A5: 月 | B5: 売上合計（円） | C5: 件数
A6: 1月 | B6: =SUMPRODUCT((ISNUMBER(【台帳】②購買記録!$B$4:$B$205))*(MONTH(IF(ISNUMBER(【台帳】②購買記録!$B$4:$B$205),【台帳】②購買記録!$B$4:$B$205,TODAY()))=1)*(【台帳】②購買記録!$H$4:$H$205)) -> 0 | C6: =SUMPRODUCT((ISNUMBER(【台帳】②購買記録!$B$4:$B$205))*(MONTH(IF(ISNUMBER(【台帳】②購買記録!$B$4:$B$205),【台帳】②購買記録!$B$4:$B$205,TODAY()))=1)*(【台帳】②購買記録!$H$4:$H$205>0)) -> 0
A7: 2月 | B7: =SUMPRODUCT((ISNUMBER(【台帳】②購買記録!$B$4:$B$205))*(MONTH(IF(ISNUMBER(【台帳】②購買記録!$B$4:$B$205),【台帳】②購買記録!$B$4:$B$205,TODAY()))=2)*(【台帳】②購買記録!$H$4:$H$205)) -> 0 | C7: =SUMPRODUCT((ISNUMBER(【台帳】②購買記録!$B$4:$B$205))*(MONTH(IF(ISNUMBER(【台帳】②購買記録!$B$4:$B$205),【台帳】②購買記録!$B$4:$B$205,TODAY()))=2)*(【台帳】②購買記録!$H$4:$H$205>0)) -> 0
A8: 3月 | B8: =SUMPRODUCT((ISNUMBER(【台帳】②購買記録!$B$4:$B$205))*(MONTH(IF(ISNUMBER(【台帳】②購買記録!$B$4:$B$205),【台帳】②購買記録!$B$4:$B$205,TODAY()))=3)*(【台帳】②購買記録!$H$4:$H$205)) -> 0 | C8: =SUMPRODUCT((ISNUMBER(【台帳】②購買記録!$B$4:$B$205))*(MONTH(IF(ISNUMBER(【台帳】②購買記録!$B$4:$B$205),【台帳】②購買記録!$B$4:$B$205,TODAY()))=3)*(【台帳】②購買記録!$H$4:$H$205>0)) -> 0
A9: 4月 | B9: =SUMPRODUCT((ISNUMBER(【台帳】②購買記録!$B$4:$B$205))*(MONTH(IF(ISNUMBER(【台帳】②購買記録!$B$4:$B$205),【台帳】②購買記録!$B$4:$B$205,TODAY()))=4)*(【台帳】②購買記録!$H$4:$H$205)) -> 0 | C9: =SUMPRODUCT((ISNUMBER(【台帳】②購買記録!$B$4:$B$205))*(MONTH(IF(ISNUMBER(【台帳】②購買記録!$B$4:$B$205),【台帳】②購買記録!$B$4:$B$205,TODAY()))=4)*(【台帳】②購買記録!$H$4:$H$205>0)) -> 0
A10: 5月 | B10: =SUMPRODUCT((ISNUMBER(【台帳】②購買記録!$B$4:$B$205))*(MONTH(IF(ISNUMBER(【台帳】②購買記録!$B$4:$B$205),【台帳】②購買記録!$B$4:$B$205,TODAY()))=5)*(【台帳】②購買記録!$H$4:$H$205)) -> 20500 | C10: =SUMPRODUCT((ISNUMBER(【台帳】②購買記録!$B$4:$B$205))*(MONTH(IF(ISNUMBER(【台帳】②購買記録!$B$4:$B$205),【台帳】②購買記録!$B$4:$B$205,TODAY()))=5)*(【台帳】②購買記録!$H$4:$H$205>0)) -> 2
A11: 6月 | B11: =SUMPRODUCT((ISNUMBER(【台帳】②購買記録!$B$4:$B$205))*(MONTH(IF(ISNUMBER(【台帳】②購買記録!$B$4:$B$205),【台帳】②購買記録!$B$4:$B$205,TODAY()))=6)*(【台帳】②購買記録!$H$4:$H$205)) -> 0 | C11: =SUMPRODUCT((ISNUMBER(【台帳】②購買記録!$B$4:$B$205))*(MONTH(IF(ISNUMBER(【台帳】②購買記録!$B$4:$B$205),【台帳】②購買記録!$B$4:$B$205,TODAY()))=6)*(【台帳】②購買記録!$H$4:$H$205>0)) -> 0
A12: 7月 | B12: =SUMPRODUCT((ISNUMBER(【台帳】②購買記録!$B$4:$B$205))*(MONTH(IF(ISNUMBER(【台帳】②購買記録!$B$4:$B$205),【台帳】②購買記録!$B$4:$B$205,TODAY()))=7)*(【台帳】②購買記録!$H$4:$H$205)) -> 0 | C12: =SUMPRODUCT((ISNUMBER(【台帳】②購買記録!$B$4:$B$205))*(MONTH(IF(ISNUMBER(【台帳】②購買記録!$B$4:$B$205),【台帳】②購買記録!$B$4:$B$205,TODAY()))=7)*(【台帳】②購買記録!$H$4:$H$205>0)) -> 0
A13: 8月 | B13: =SUMPRODUCT((ISNUMBER(【台帳】②購買記録!$B$4:$B$205))*(MONTH(IF(ISNUMBER(【台帳】②購買記録!$B$4:$B$205),【台帳】②購買記録!$B$4:$B$205,TODAY()))=8)*(【台帳】②購買記録!$H$4:$H$205)) -> 0 | C13: =SUMPRODUCT((ISNUMBER(【台帳】②購買記録!$B$4:$B$205))*(MONTH(IF(ISNUMBER(【台帳】②購買記録!$B$4:$B$205),【台帳】②購買記録!$B$4:$B$205,TODAY()))=8)*(【台帳】②購買記録!$H$4:$H$205>0)) -> 0
A14: 9月 | B14: =SUMPRODUCT((ISNUMBER(【台帳】②購買記録!$B$4:$B$205))*(MONTH(IF(ISNUMBER(【台帳】②購買記録!$B$4:$B$205),【台帳】②購買記録!$B$4:$B$205,TODAY()))=9)*(【台帳】②購買記録!$H$4:$H$205)) -> 0 | C14: =SUMPRODUCT((ISNUMBER(【台帳】②購買記録!$B$4:$B$205))*(MONTH(IF(ISNUMBER(【台帳】②購買記録!$B$4:$B$205),【台帳】②購買記録!$B$4:$B$205,TODAY()))=9)*(【台帳】②購買記録!$H$4:$H$205>0)) -> 0
A15: 10月 | B15: =SUMPRODUCT((ISNUMBER(【台帳】②購買記録!$B$4:$B$205))*(MONTH(IF(ISNUMBER(【台帳】②購買記録!$B$4:$B$205),【台帳】②購買記録!$B$4:$B$205,TODAY()))=10)*(【台帳】②購買記録!$H$4:$H$205)) -> 0 | C15: =SUMPRODUCT((ISNUMBER(【台帳】②購買記録!$B$4:$B$205))*(MONTH(IF(ISNUMBER(【台帳】②購買記録!$B$4:$B$205),【台帳】②購買記録!$B$4:$B$205,TODAY()))=10)*(【台帳】②購買記録!$H$4:$H$205>0)) -> 0
A16: 11月 | B16: =SUMPRODUCT((ISNUMBER(【台帳】②購買記録!$B$4:$B$205))*(MONTH(IF(ISNUMBER(【台帳】②購買記録!$B$4:$B$205),【台帳】②購買記録!$B$4:$B$205,TODAY()))=11)*(【台帳】②購買記録!$H$4:$H$205)) -> 0 | C16: =SUMPRODUCT((ISNUMBER(【台帳】②購買記録!$B$4:$B$205))*(MONTH(IF(ISNUMBER(【台帳】②購買記録!$B$4:$B$205),【台帳】②購買記録!$B$4:$B$205,TODAY()))=11)*(【台帳】②購買記録!$H$4:$H$205>0)) -> 0
A17: 12月 | B17: =SUMPRODUCT((ISNUMBER(【台帳】②購買記録!$B$4:$B$205))*(MONTH(IF(ISNUMBER(【台帳】②購買記録!$B$4:$B$205),【台帳】②購買記録!$B$4:$B$205,TODAY()))=12)*(【台帳】②購買記録!$H$4:$H$205)) -> 0 | C17: =SUMPRODUCT((ISNUMBER(【台帳】②購買記録!$B$4:$B$205))*(MONTH(IF(ISNUMBER(【台帳】②購買記録!$B$4:$B$205),【台帳】②購買記録!$B$4:$B$205,TODAY()))=12)*(【台帳】②購買記録!$H$4:$H$205>0)) -> 0
A18: 年間合計 | B18: =SUM(B6:B17) -> 20500 | C18: =SUM(C6:C17) -> 2
A20: 顧客別売上TOP10
A21: 顧客ID | B21: 顧客名 | C21: 購買金額合計（円） | D21: 購買件数
A22: ※ ②購買記録シートをコピーし、ピボットテーブルで顧客ID別集計をお試しください

Sheet 【会員】①会員マスタ
A1: 【会員型】① 会員マスタ ― 会員情報と契約内容を登録します
A2: ※ ステータス列でメンバーの状態を管理します。退会者は自動で色が変わります。
A3: 会員ID | B3: 氏名 | C3: フリガナ | D3: 電話番号 | E3: メールアドレス | F3: プラン | G3: 月額（円） | H3: 開始日 | I3: ステータス | J3: 備考
A4: M001 | B4: 田中一郎 | C4: タナカイチロウ | D4: 090-1111-2222 | E4: tanaka@example.com | F4: スタンダード | G4: 5000 | H4: 46023 | I4: 在籍
A5: M002 | B5: 山本二郎 | C5: ヤマモトジロウ | D5: 080-3333-4444 | E5: yamamoto@example.com | F5: プレミアム | G5: 10000 | H5: 46054 | I5: 休会 | J5: 育児休暇中
G6: =IFERROR(VLOOKUP(F6,【会員】③プランマスタ!$A$4:$B$20,2,0),"")
G7: =IFERROR(VLOOKUP(F7,【会員】③プランマスタ!$A$4:$B$20,2,0),"")
G8: =IFERROR(VLOOKUP(F8,【会員】③プランマスタ!$A$4:$B$20,2,0),"")
G9: =IFERROR(VLOOKUP(F9,【会員】③プランマスタ!$A$4:$B$20,2,0),"")
G10: =IFERROR(VLOOKUP(F10,【会員】③プランマスタ!$A$4:$B$20,2,0),"")
G11: =IFERROR(VLOOKUP(F11,【会員】③プランマスタ!$A$4:$B$20,2,0),"")
G12: =IFERROR(VLOOKUP(F12,【会員】③プランマスタ!$A$4:$B$20,2,0),"")
G13: =IFERROR(VLOOKUP(F13,【会員】③プランマスタ!$A$4:$B$20,2,0),"")
G14: =IFERROR(VLOOKUP(F14,【会員】③プランマスタ!$A$4:$B$20,2,0),"")
G15: =IFERROR(VLOOKUP(F15,【会員】③プランマスタ!$A$4:$B$20,2,0),"")
G16: =IFERROR(VLOOKUP(F16,【会員】③プランマスタ!$A$4:$B$20,2,0),"")
G17: =IFERROR(VLOOKUP(F17,【会員】③プランマスタ!$A$4:$B$20,2,0),"")
... G105: =IFERROR(VLOOKUP(F105,【会員】③プランマスタ!$A$4:$B$20,2,0),"")

Sheet 【会員】②CSVペースト
A1: 【会員型】② CSVペースト ― 金融機関の入金データをここに貼り付けてください
A2: ※ 列の順序：日付 → 摘要（会社名・氏名）→ 金額（プラス値） の順に貼ってください ③引落し管理シートで会員情報と自動照合されます
A3: 日付 | B3: 摘要（振込人名など） | C3: 金額（円） | D3: 残高（円） | E3: 備考
A4: 46198 | B4: タナカ イチロウ | C4: 5000
A5: 46198 | B5: ヤマモト ジロウ | C5: 10000
A6: 46199 | B6: サトウ サブロウ | C6: 5000

Sheet 【会員】③引落し管理
A1: 【会員型】③ 引落し管理 ― 会員マスタ×CSVデータを照合して入金状況を確認します
A2: ※ 対象月・会員IDを入力してください。②CSVペーストに貼ったデータと照合し「状態」列に自動判定されます
A3: 対象月 | B3: 46174 | C3: ← ここに対象月を入力（例：2026/06）すると照合基準月が変わります
A4: 会員ID | B4: 氏名（自動） | C4: プラン（自動） | D4: 請求金額（自動） | E4: 摘要キーワード | F4: 照合結果（自動） | G4: 入金金額（自動） | H4: 差額（自動） | I4: 状態 | J4: 備考
B5: =IFERROR(VLOOKUP(A5,【会員】①会員マスタ!$A$4:$J$105,2,0),"") | C5: =IFERROR(VLOOKUP(A5,【会員】①会員マスタ!$A$4:$J$105,6,0),"") | D5: =IFERROR(VLOOKUP(A5,【会員】①会員マスタ!$A$4:$J$105,7,0),"") | E5: =IFERROR(VLOOKUP(A5,【会員】①会員マスタ!$A$4:$J$105,3,0),"") | F5: =IFERROR(SUMPRODUCT((ISNUMBER(SEARCH(E5,【会員】②CSVペースト!$B$4:$B$103)))*(ISNUMBER(【会員】②CSVペースト!$A$4:$A$103))*(MONTH(【会員】②CSVペースト!$A$4:$A$103)=MONTH($B$3))*(YEAR(【会員】②CSVペースト!$A$4:$A$103)=YEAR($B$3))*(【会員】②CSVペースト!$C$4:$C$103)),"") -> 20000 | G5: =IFERROR(F5,"") -> 20000 | H5: =IFERROR(IF(AND(D5<>"",G5<>""),D5-G5,""),"") | I5: =IF(A5="","",IF(G5="","未入金",IF(H5=0,"入金済",IF(H5>0,"一部入金","要確認"))))
B6: =IFERROR(VLOOKUP(A6,【会員】①会員マスタ!$A$4:$J$105,2,0),"") | C6: =IFERROR(VLOOKUP(A6,【会員】①会員マスタ!$A$4:$J$105,6,0),"") | D6: =IFERROR(VLOOKUP(A6,【会員】①会員マスタ!$A$4:$J$105,7,0),"") | E6: =IFERROR(VLOOKUP(A6,【会員】①会員マスタ!$A$4:$J$105,3,0),"") | F6: =IFERROR(SUMPRODUCT((ISNUMBER(SEARCH(E6,【会員】②CSVペースト!$B$4:$B$103)))*(ISNUMBER(【会員】②CSVペースト!$A$4:$A$103))*(MONTH(【会員】②CSVペースト!$A$4:$A$103)=MONTH($B$3))*(YEAR(【会員】②CSVペースト!$A$4:$A$103)=YEAR($B$3))*(【会員】②CSVペースト!$C$4:$C$103)),"") -> 20000 | G6: =IFERROR(F6,"") -> 20000 | H6: =IFERROR(IF(AND(D6<>"",G6<>""),D6-G6,""),"") | I6: =IF(A6="","",IF(G6="","未入金",IF(H6=0,"入金済",IF(H6>0,"一部入金","要確認"))))
B7: =IFERROR(VLOOKUP(A7,【会員】①会員マスタ!$A$4:$J$105,2,0),"") | C7: =IFERROR(VLOOKUP(A7,【会員】①会員マスタ!$A$4:$J$105,6,0),"") | D7: =IFERROR(VLOOKUP(A7,【会員】①会員マスタ!$A$4:$J$105,7,0),"") | E7: =IFERROR(VLOOKUP(A7,【会員】①会員マスタ!$A$4:$J$105,3,0),"") | F7: =IFERROR(SUMPRODUCT((ISNUMBER(SEARCH(E7,【会員】②CSVペースト!$B$4:$B$103)))*(ISNUMBER(【会員】②CSVペースト!$A$4:$A$103))*(MONTH(【会員】②CSVペースト!$A$4:$A$103)=MONTH($B$3))*(YEAR(【会員】②CSVペースト!$A$4:$A$103)=YEAR($B$3))*(【会員】②CSVペースト!$C$4:$C$103)),"") -> 20000 | G7: =IFERROR(F7,"") -> 20000 | H7: =IFERROR(IF(AND(D7<>"",G7<>""),D7-G7,""),"") | I7: =IF(A7="","",IF(G7="","未入金",IF(H7=0,"入金済",IF(H7>0,"一部入金","要確認"))))
B8: =IFERROR(VLOOKUP(A8,【会員】①会員マスタ!$A$4:$J$105,2,0),"") | C8: =IFERROR(VLOOKUP(A8,【会員】①会員マスタ!$A$4:$J$105,6,0),"") | D8: =IFERROR(VLOOKUP(A8,【会員】①会員マスタ!$A$4:$J$105,7,0),"") | E8: =IFERROR(VLOOKUP(A8,【会員】①会員マスタ!$A$4:$J$105,3,0),"") | F8: =IFERROR(SUMPRODUCT((ISNUMBER(SEARCH(E8,【会員】②CSVペースト!$B$4:$B$103)))*(ISNUMBER(【会員】②CSVペースト!$A$4:$A$103))*(MONTH(【会員】②CSVペースト!$A$4:$A$103)=MONTH($B$3))*(YEAR(【会員】②CSVペースト!$A$4:$A$103)=YEAR($B$3))*(【会員】②CSVペースト!$C$4:$C$103)),"") -> 20000 | G8: =IFERROR(F8,"") -> 20000 | H8: =IFERROR(IF(AND(D8<>"",G8<>""),D8-G8,""),"") | I8: =IF(A8="","",IF(G8="","未入金",IF(H8=0,"入金済",IF(H8>0,"一部入金","要確認"))))
B9: =IFERROR(VLOOKUP(A9,【会員】①会員マスタ!$A$4:$J$105,2,0),"") | C9: =IFERROR(VLOOKUP(A9,【会員】①会員マスタ!$A$4:$J$105,6,0),"") | D9: =IFERROR(VLOOKUP(A9,【会員】①会員マスタ!$A$4:$J$105,7,0),"") | E9: =IFERROR(VLOOKUP(A9,【会員】①会員マスタ!$A$4:$J$105,3,0),"") | F9: =IFERROR(SUMPRODUCT((ISNUMBER(SEARCH(E9,【会員】②CSVペースト!$B$4:$B$103)))*(ISNUMBER(【会員】②CSVペースト!$A$4:$A$103))*(MONTH(【会員】②CSVペースト!$A$4:$A$103)=MONTH($B$3))*(YEAR(【会員】②CSVペースト!$A$4:$A$103)=YEAR($B$3))*(【会員】②CSVペースト!$C$4:$C$103)),"") -> 20000 | G9: =IFERROR(F9,"") -> 20000 | H9: =IFERROR(IF(AND(D9<>"",G9<>""),D9-G9,""),"") | I9: =IF(A9="","",IF(G9="","未入金",IF(H9=0,"入金済",IF(H9>0,"一部入金","要確認"))))
B10: =IFERROR(VLOOKUP(A10,【会員】①会員マスタ!$A$4:$J$105,2,0),"") | C10: =IFERROR(VLOOKUP(A10,【会員】①会員マスタ!$A$4:$J$105,6,0),"") | D10: =IFERROR(VLOOKUP(A10,【会員】①会員マスタ!$A$4:$J$105,7,0),"") | E10: =IFERROR(VLOOKUP(A10,【会員】①会員マスタ!$A$4:$J$105,3,0),"") | F10: =IFERROR(SUMPRODUCT((ISNUMBER(SEARCH(E10,【会員】②CSVペースト!$B$4:$B$103)))*(ISNUMBER(【会員】②CSVペースト!$A$4:$A$103))*(MONTH(【会員】②CSVペースト!$A$4:$A$103)=MONTH($B$3))*(YEAR(【会員】②CSVペースト!$A$4:$A$103)=YEAR($B$3))*(【会員】②CSVペースト!$C$4:$C$103)),"") -> 20000 | G10: =IFERROR(F10,"") -> 20000 | H10: =IFERROR(IF(AND(D10<>"",G10<>""),D10-G10,""),"") | I10: =IF(A10="","",IF(G10="","未入金",IF(H10=0,"入金済",IF(H10>0,"一部入金","要確認"))))
B11: =IFERROR(VLOOKUP(A11,【会員】①会員マスタ!$A$4:$J$105,2,0),"") | C11: =IFERROR(VLOOKUP(A11,【会員】①会員マスタ!$A$4:$J$105,6,0),"") | D11: =IFERROR(VLOOKUP(A11,【会員】①会員マスタ!$A$4:$J$105,7,0),"") | E11: =IFERROR(VLOOKUP(A11,【会員】①会員マスタ!$A$4:$J$105,3,0),"") | F11: =IFERROR(SUMPRODUCT((ISNUMBER(SEARCH(E11,【会員】②CSVペースト!$B$4:$B$103)))*(ISNUMBER(【会員】②CSVペースト!$A$4:$A$103))*(MONTH(【会員】②CSVペースト!$A$4:$A$103)=MONTH($B$3))*(YEAR(【会員】②CSVペースト!$A$4:$A$103)=YEAR($B$3))*(【会員】②CSVペースト!$C$4:$C$103)),"") -> 20000 | G11: =IFERROR(F11,"") -> 20000 | H11: =IFERROR(IF(AND(D11<>"",G11<>""),D11-G11,""),"") | I11: =IF(A11="","",IF(G11="","未入金",IF(H11=0,"入金済",IF(H11>0,"一部入金","要確認"))))
B12: =IFERROR(VLOOKUP(A12,【会員】①会員マスタ!$A$4:$J$105,2,0),"") | C12: =IFERROR(VLOOKUP(A12,【会員】①会員マスタ!$A$4:$J$105,6,0),"") | D12: =IFERROR(VLOOKUP(A12,【会員】①会員マスタ!$A$4:$J$105,7,0),"") | E12: =IFERROR(VLOOKUP(A12,【会員】①会員マスタ!$A$4:$J$105,3,0),"") | F12: =IFERROR(SUMPRODUCT((ISNUMBER(SEARCH(E12,【会員】②CSVペースト!$B$4:$B$103)))*(ISNUMBER(【会員】②CSVペースト!$A$4:$A$103))*(MONTH(【会員】②CSVペースト!$A$4:$A$103)=MONTH($B$3))*(YEAR(【会員】②CSVペースト!$A$4:$A$103)=YEAR($B$3))*(【会員】②CSVペースト!$C$4:$C$103)),"") -> 20000 | G12: =IFERROR(F12,"") -> 20000 | H12: =IFERROR(IF(AND(D12<>"",G12<>""),D12-G12,""),"") | I12: =IF(A12="","",IF(G12="","未入金",IF(H12=0,"入金済",IF(H12>0,"一部入金","要確認"))))
B13: =IFERROR(VLOOKUP(A13,【会員】①会員マスタ!$A$4:$J$105,2,0),"") | C13: =IFERROR(VLOOKUP(A13,【会員】①会員マスタ!$A$4:$J$105,6,0),"") | D13: =IFERROR(VLOOKUP(A13,【会員】①会員マスタ!$A$4:$J$105,7,0),"") | E13: =IFERROR(VLOOKUP(A13,【会員】①会員マスタ!$A$4:$J$105,3,0),"") | F13: =IFERROR(SUMPRODUCT((ISNUMBER(SEARCH(E13,【会員】②CSVペースト!$B$4:$B$103)))*(ISNUMBER(【会員】②CSVペースト!$A$4:$A$103))*(MONTH(【会員】②CSVペースト!$A$4:$A$103)=MONTH($B$3))*(YEAR(【会員】②CSVペースト!$A$4:$A$103)=YEAR($B$3))*(【会員】②CSVペースト!$C$4:$C$103)),"") -> 20000 | G13: =IFERROR(F13,"") -> 20000 | H13: =IFERROR(IF(AND(D13<>"",G13<>""),D13-G13,""),"") | I13: =IF(A13="","",IF(G13="","未入金",IF(H13=0,"入金済",IF(H13>0,"一部入金","要確認"))))
B14: =IFERROR(VLOOKUP(A14,【会員】①会員マスタ!$A$4:$J$105,2,0),"") | C14: =IFERROR(VLOOKUP(A14,【会員】①会員マスタ!$A$4:$J$105,6,0),"") | D14: =IFERROR(VLOOKUP(A14,【会員】①会員マスタ!$A$4:$J$105,7,0),"") | E14: =IFERROR(VLOOKUP(A14,【会員】①会員マスタ!$A$4:$J$105,3,0),"") | F14: =IFERROR(SUMPRODUCT((ISNUMBER(SEARCH(E14,【会員】②CSVペースト!$B$4:$B$103)))*(ISNUMBER(【会員】②CSVペースト!$A$4:$A$103))*(MONTH(【会員】②CSVペースト!$A$4:$A$103)=MONTH($B$3))*(YEAR(【会員】②CSVペースト!$A$4:$A$103)=YEAR($B$3))*(【会員】②CSVペースト!$C$4:$C$103)),"") -> 20000 | G14: =IFERROR(F14,"") -> 20000 | H14: =IFERROR(IF(AND(D14<>"",G14<>""),D14-G14,""),"") | I14: =IF(A14="","",IF(G14="","未入金",IF(H14=0,"入金済",IF(H14>0,"一部入金","要確認"))))
B15: =IFERROR(VLOOKUP(A15,【会員】①会員マスタ!$A$4:$J$105,2,0),"") | C15: =IFERROR(VLOOKUP(A15,【会員】①会員マスタ!$A$4:$J$105,6,0),"") | D15: =IFERROR(VLOOKUP(A15,【会員】①会員マスタ!$A$4:$J$105,7,0),"") | E15: =IFERROR(VLOOKUP(A15,【会員】①会員マスタ!$A$4:$J$105,3,0),"") | F15: =IFERROR(SUMPRODUCT((ISNUMBER(SEARCH(E15,【会員】②CSVペースト!$B$4:$B$103)))*(ISNUMBER(【会員】②CSVペースト!$A$4:$A$103))*(MONTH(【会員】②CSVペースト!$A$4:$A$103)=MONTH($B$3))*(YEAR(【会員】②CSVペースト!$A$4:$A$103)=YEAR($B$3))*(【会員】②CSVペースト!$C$4:$C$103)),"") -> 20000 | G15: =IFERROR(F15,"") -> 20000 | H15: =IFERROR(IF(AND(D15<>"",G15<>""),D15-G15,""),"") | I15: =IF(A15="","",IF(G15="","未入金",IF(H15=0,"入金済",IF(H15>0,"一部入金","要確認"))))
B16: =IFERROR(VLOOKUP(A16,【会員】①会員マスタ!$A$4:$J$105,2,0),"") | C16: =IFERROR(VLOOKUP(A16,【会員】①会員マスタ!$A$4:$J$105,6,0),"") | D16: =IFERROR(VLOOKUP(A16,【会員】①会員マスタ!$A$4:$J$105,7,0),"") | E16: =IFERROR(VLOOKUP(A16,【会員】①会員マスタ!$A$4:$J$105,3,0),"") | F16: =IFERROR(SUMPRODUCT((ISNUMBER(SEARCH(E16,【会員】②CSVペースト!$B$4:$B$103)))*(ISNUMBER(【会員】②CSVペースト!$A$4:$A$103))*(MONTH(【会員】②CSVペースト!$A$4:$A$103)=MONTH($B$3))*(YEAR(【会員】②CSVペースト!$A$4:$A$103)=YEAR($B$3))*(【会員】②CSVペースト!$C$4:$C$103)),"") -> 20000 | G16: =IFERROR(F16,"") -> 20000 | H16: =IFERROR(IF(AND(D16<>"",G16<>""),D16-G16,""),"") | I16: =IF(A16="","",IF(G16="","未入金",IF(H16=0,"入金済",IF(H16>0,"一部入金","要確認"))))
... B104: =IFERROR(VLOOKUP(A104,【会員】①会員マスタ!$A$4:$J$105,2,0),"") | C104: =IFERROR(VLOOKUP(A104,【会員】①会員マスタ!$A$4:$J$105,6,0),"") | D104: =IFERROR(VLOOKUP(A104,【会員】①会員マスタ!$A$4:$J$105,7,0),"") | E104: =IFERROR(VLOOKUP(A104,【会員】①会員マスタ!$A$4:$J$105,3,0),"") | F104: =IFERROR(SUMPRODUCT((ISNUMBER(SEARCH(E104,【会員】②CSVペースト!$B$4:$B$103)))*(ISNUMBER(【会員】②CSVペースト!$A$4:$A$103))*(MONTH(【会員】②CSVペースト!$A$4:$A$103)=MONTH($B$3))*(YEAR(【会員】②CSVペースト!$A$4:$A$103)=YEAR($B$3))*(【会員】②CSVペースト!$C$4:$C$103)),"") -> 20000 | G104: =IFERROR(F104,"") -> 20000 | H104: =IFERROR(IF(AND(D104<>"",G104<>""),D104-G104,""),"") | I104: =IF(A104="","",IF(G104="","未入金",IF(H104=0,"入金済",IF(H104>0,"一部入金","要確認"))))

Sheet 【会員】③プランマスタ
A1: 【会員型】③ プランマスタ ― プラン名と月額を登録します
A2: ※ プラン名は①会員マスタのプラン列でドロップダウン選択できます。
A3: プラン名 | B3: 月額（円） | C3: 内容・特典 | D3: 備考
A4: ライト | B4: 3000 | C4: 月2回利用可・基本サービス
A5: スタンダード | B5: 5000 | C5: 月4回利用可・基本サービス＋優先予約
A6: プレミアム | B6: 10000 | C6: 無制限利用・全サービス＋専任担当

Sheet 【会員】④売上分析
A1: 【会員型】④ 売上分析 ― 月別会費収入とプラン別構成を確認できます
A2: ※ ②引落し管理シートの「済」データから自動集計されます。
A4: 月別会費収入
A5: 月 | B5: 収入合計（円） | C5: 会員数
A6: 1月 | B6: =IFERROR(SUMPRODUCT(([1]【会員】②引落し管理!$I$4:$I$203="済")*(ISNUMBER([1]【会員】②引落し管理!$B$4:$B$203))*(MONTH([1]【会員】②引落し管理!$B$4:$B$203)=1)*([1]【会員】②引落し管理!$F$4:$F$203)),0) -> 0 | C6: =IFERROR(SUMPRODUCT(([1]【会員】②引落し管理!$I$4:$I$203="済")*(ISNUMBER([1]【会員】②引落し管理!$B$4:$B$203))*(MONTH([1]【会員】②引落し管理!$B$4:$B$203)=1)),0) -> 0
A7: 2月 | B7: =IFERROR(SUMPRODUCT(([1]【会員】②引落し管理!$I$4:$I$203="済")*(ISNUMBER([1]【会員】②引落し管理!$B$4:$B$203))*(MONTH([1]【会員】②引落し管理!$B$4:$B$203)=2)*([1]【会員】②引落し管理!$F$4:$F$203)),0) -> 0 | C7: =IFERROR(SUMPRODUCT(([1]【会員】②引落し管理!$I$4:$I$203="済")*(ISNUMBER([1]【会員】②引落し管理!$B$4:$B$203))*(MONTH([1]【会員】②引落し管理!$B$4:$B$203)=2)),0) -> 0
A8: 3月 | B8: =IFERROR(SUMPRODUCT(([1]【会員】②引落し管理!$I$4:$I$203="済")*(ISNUMBER([1]【会員】②引落し管理!$B$4:$B$203))*(MONTH([1]【会員】②引落し管理!$B$4:$B$203)=3)*([1]【会員】②引落し管理!$F$4:$F$203)),0) -> 0 | C8: =IFERROR(SUMPRODUCT(([1]【会員】②引落し管理!$I$4:$I$203="済")*(ISNUMBER([1]【会員】②引落し管理!$B$4:$B$203))*(MONTH([1]【会員】②引落し管理!$B$4:$B$203)=3)),0) -> 0
A9: 4月 | B9: =IFERROR(SUMPRODUCT(([1]【会員】②引落し管理!$I$4:$I$203="済")*(ISNUMBER([1]【会員】②引落し管理!$B$4:$B$203))*(MONTH([1]【会員】②引落し管理!$B$4:$B$203)=4)*([1]【会員】②引落し管理!$F$4:$F$203)),0) -> 0 | C9: =IFERROR(SUMPRODUCT(([1]【会員】②引落し管理!$I$4:$I$203="済")*(ISNUMBER([1]【会員】②引落し管理!$B$4:$B$203))*(MONTH([1]【会員】②引落し管理!$B$4:$B$203)=4)),0) -> 0
A10: 5月 | B10: =IFERROR(SUMPRODUCT(([1]【会員】②引落し管理!$I$4:$I$203="済")*(ISNUMBER([1]【会員】②引落し管理!$B$4:$B$203))*(MONTH([1]【会員】②引落し管理!$B$4:$B$203)=5)*([1]【会員】②引落し管理!$F$4:$F$203)),0) -> 0 | C10: =IFERROR(SUMPRODUCT(([1]【会員】②引落し管理!$I$4:$I$203="済")*(ISNUMBER([1]【会員】②引落し管理!$B$4:$B$203))*(MONTH([1]【会員】②引落し管理!$B$4:$B$203)=5)),0) -> 0
A11: 6月 | B11: =IFERROR(SUMPRODUCT(([1]【会員】②引落し管理!$I$4:$I$203="済")*(ISNUMBER([1]【会員】②引落し管理!$B$4:$B$203))*(MONTH([1]【会員】②引落し管理!$B$4:$B$203)=6)*([1]【会員】②引落し管理!$F$4:$F$203)),0) -> 0 | C11: =IFERROR(SUMPRODUCT(([1]【会員】②引落し管理!$I$4:$I$203="済")*(ISNUMBER([1]【会員】②引落し管理!$B$4:$B$203))*(MONTH([1]【会員】②引落し管理!$B$4:$B$203)=6)),0) -> 0
A12: 7月 | B12: =IFERROR(SUMPRODUCT(([1]【会員】②引落し管理!$I$4:$I$203="済")*(ISNUMBER([1]【会員】②引落し管理!$B$4:$B$203))*(MONTH([1]【会員】②引落し管理!$B$4:$B$203)=7)*([1]【会員】②引落し管理!$F$4:$F$203)),0) -> 0 | C12: =IFERROR(SUMPRODUCT(([1]【会員】②引落し管理!$I$4:$I$203="済")*(ISNUMBER([1]【会員】②引落し管理!$B$4:$B$203))*(MONTH([1]【会員】②引落し管理!$B$4:$B$203)=7)),0) -> 0
A13: 8月 | B13: =IFERROR(SUMPRODUCT(([1]【会員】②引落し管理!$I$4:$I$203="済")*(ISNUMBER([1]【会員】②引落し管理!$B$4:$B$203))*(MONTH([1]【会員】②引落し管理!$B$4:$B$203)=8)*([1]【会員】②引落し管理!$F$4:$F$203)),0) -> 0 | C13: =IFERROR(SUMPRODUCT(([1]【会員】②引落し管理!$I$4:$I$203="済")*(ISNUMBER([1]【会員】②引落し管理!$B$4:$B$203))*(MONTH([1]【会員】②引落し管理!$B$4:$B$203)=8)),0) -> 0
A14: 9月 | B14: =IFERROR(SUMPRODUCT(([1]【会員】②引落し管理!$I$4:$I$203="済")*(ISNUMBER([1]【会員】②引落し管理!$B$4:$B$203))*(MONTH([1]【会員】②引落し管理!$B$4:$B$203)=9)*([1]【会員】②引落し管理!$F$4:$F$203)),0) -> 0 | C14: =IFERROR(SUMPRODUCT(([1]【会員】②引落し管理!$I$4:$I$203="済")*(ISNUMBER([1]【会員】②引落し管理!$B$4:$B$203))*(MONTH([1]【会員】②引落し管理!$B$4:$B$203)=9)),0) -> 0
A15: 10月 | B15: =IFERROR(SUMPRODUCT(([1]【会員】②引落し管理!$I$4:$I$203="済")*(ISNUMBER([1]【会員】②引落し管理!$B$4:$B$203))*(MONTH([1]【会員】②引落し管理!$B$4:$B$203)=10)*([1]【会員】②引落し管理!$F$4:$F$203)),0) -> 0 | C15: =IFERROR(SUMPRODUCT(([1]【会員】②引落し管理!$I$4:$I$203="済")*(ISNUMBER([1]【会員】②引落し管理!$B$4:$B$203))*(MONTH([1]【会員】②引落し管理!$B$4:$B$203)=10)),0) -> 0
A16: 11月 | B16: =IFERROR(SUMPRODUCT(([1]【会員】②引落し管理!$I$4:$I$203="済")*(ISNUMBER([1]【会員】②引落し管理!$B$4:$B$203))*(MONTH([1]【会員】②引落し管理!$B$4:$B$203)=11)*([1]【会員】②引落し管理!$F$4:$F$203)),0) -> 0 | C16: =IFERROR(SUMPRODUCT(([1]【会員】②引落し管理!$I$4:$I$203="済")*(ISNUMBER([1]【会員】②引落し管理!$B$4:$B$203))*(MONTH([1]【会員】②引落し管理!$B$4:$B$203)=11)),0) -> 0
A17: 12月 | B17: =IFERROR(SUMPRODUCT(([1]【会員】②引落し管理!$I$4:$I$203="済")*(ISNUMBER([1]【会員】②引落し管理!$B$4:$B$203))*(MONTH([1]【会員】②引落し管理!$B$4:$B$203)=12)*([1]【会員】②引落し管理!$F$4:$F$203)),0) -> 0 | C17: =IFERROR(SUMPRODUCT(([1]【会員】②引落し管理!$I$4:$I$203="済")*(ISNUMBER([1]【会員】②引落し管理!$B$4:$B$203))*(MONTH([1]【会員】②引落し管理!$B$4:$B$203)=12)),0) -> 0
A18: 年間合計 | B18: =SUM(B6:B17) -> 0 | C18: =SUM(C6:C17) -> 0
A20: プラン別会員構成
A21: プラン名 | B21: 会員数 | C21: 構成比
A22: =IFERROR(【会員】③プランマスタ!A4,"") -> ライト | B22: =COUNTIFS(【会員】①会員マスタ!$F$4:$F$105,A22,【会員】①会員マスタ!$I$4:$I$105,"在籍") -> 0 | C22: =IFERROR(B22/SUM($B$22:$B$24),"") -> 0
A23: =IFERROR(【会員】③プランマスタ!A5,"") -> スタンダード | B23: =COUNTIFS(【会員】①会員マスタ!$F$4:$F$105,A23,【会員】①会員マスタ!$I$4:$I$105,"在籍") -> 1 | C23: =IFERROR(B23/SUM($B$22:$B$24),"") -> 1
A24: =IFERROR(【会員】③プランマスタ!A6,"") -> プレミアム | B24: =COUNTIFS(【会員】①会員マスタ!$F$4:$F$105,A24,【会員】①会員マスタ!$I$4:$I$105,"在籍") -> 0 | C24: =IFERROR(B24/SUM($B$22:$B$24),"") -> 0
