Workbook

Sheet 📋 使い方ガイド
B2: ⑤ 在庫・仕入れ管理
B3: 商品マスタ・仕入先・入出庫・在庫残高・棚卸しをまとめて管理するテンプレートです
B5: 📂 シート構成
B6: シート名 | C6: 役割 | D6: 主な操作・入力
B7: ①商品マスタ | C7: 商品・価格・在庫管理フラグを登録 | D7: 「在庫管理」列で「管理する」にした商品だけ⑤在庫残高でアラートが出る
B8: ②仕入先マスタ | C8: 仕入先情報と発注履歴を管理 | D8: 仕入先IDは③入庫管理で参照される。発注履歴も同シートで確認できる
B9: ③入庫管理 | C9: 仕入れ・入荷の記録 | D9: 商品IDを入力すると商品名・単価が自動表示。⑤在庫残高に自動反映
B10: ④出庫管理 | C10: 販売・払出しの記録 | D10: 商品IDを入力すると商品名が自動表示。⑤在庫残高に自動反映
B11: ⑤在庫残高 | C11: 入庫－出庫で現在庫数を自動計算・アラート表示 | D11: 「管理する」商品のみアラート対象。最低在庫を下回ると赤くなる
B12: ⑥棚卸しシート | C12: 定期的な実在庫確認と差異チェック | D12: 帳簿在庫（⑤自動参照）と実在庫を比較して差異を確認する
B15: 🔗 データの流れ（シート間のつながり）
B16: 入力元シート | C16: 参照先シート | D16: つながりの内容
B17: ①商品マスタ | C17: ③入庫管理 | D17: 商品IDで商品名・標準仕入単価を自動参照
B18: ①商品マスタ | C18: ④出庫管理 | D18: 商品IDで商品名・販売単価を自動参照
B19: ①商品マスタ | C19: ⑤在庫残高 | D19: 最低在庫数・在庫管理フラグをアラート判定に使用
B20: ②仕入先マスタ | C20: ③入庫管理 | D20: 仕入先IDで仕入先名を自動参照
B21: ③入庫管理 | C21: ⑤在庫残高 | D21: 商品ごとの入庫数合計を在庫残高に反映
B22: ④出庫管理 | C22: ⑤在庫残高 | D22: 商品ごとの出庫数合計を在庫残高に反映
B23: ⑤在庫残高 | C23: ⑥棚卸しシート | D23: 帳簿在庫数を棚卸しシートに自動参照
B26: 💡 青字のセルは自動計算セルです。直接入力すると数式が消えるためご注意ください。
B27: 💡 ①商品マスタの「在庫管理」列を「管理する」にした商品だけ⑤でアラートが表示されます。

Sheet ①商品マスタ
A1: ① 商品マスタ ― 商品・価格・在庫管理フラグを登録します
A2: ※ 「在庫管理」列を「管理する」にした商品だけ⑤在庫残高でアラートが表示されます（デフォルト：管理する）
A3: 商品ID | B3: 商品名 | C3: 規格・単位 | D3: 仕入単価（円） | E3: 販売単価（円） | F3: 仕入先ID | G3: 最低在庫数 | H3: 在庫管理 | I3: 備考
A4: P001 | B4: 商品A | C4: 個 | D4: 500 | E4: 1200 | F4: S001 | G4: 10 | H4: 管理する
A5: P002 | B5: 商品B | C5: 箱 | D5: 2000 | E5: 4500 | F5: S001 | G5: 5 | H5: 管理する
A6: P003 | B6: 商品C | C6: 個 | D6: 300 | E6: 800 | F6: S002 | G6: 0 | H6: 管理しない | I6: 消耗品
H7: 管理する
H8: 管理する
H9: 管理する
H10: 管理する
H11: 管理する
H12: 管理する
H13: 管理する
H14: 管理する
H15: 管理する
H16: 管理する
H17: 管理する
H18: 管理する
... H106: 管理する

Sheet ②仕入先マスタ
A1: ② 仕入先マスタ ― 仕入先情報を登録します
A2: ※ 仕入先IDは③入庫管理で参照されます。
A3: 仕入先ID | B3: 会社名 | C3: 担当者 | D3: 電話番号 | E3: メールアドレス | F3: 支払サイクル | G3: 備考
A4: S001 | B4: 〇〇商事 | C4: 山田太郎 | D4: 03-XXXX-XXXX | E4: yamada@example.com | F4: 月末払い
A5: S002 | B5: △△卸売 | C5: 鈴木花子 | D5: 06-XXXX-XXXX | E5: suzuki@example.com | F5: 都度払い

Sheet ③入庫管理
A1: ③ 入庫管理 ― 仕入れ・入荷を記録します
A2: ※ 商品IDを入力すると商品名・仕入単価が自動表示されます。⑤在庫残高に自動反映されます。
A3: 入庫ID | B3: 入庫日 | C3: 商品ID | D3: 商品名（自動） | E3: 数量 | F3: 仕入単価（自動） | G3: 仕入金額（自動） | H3: 仕入先ID | I3: 仕入先名（自動） | J3: 備考
A4: IN001 | B4: 46174 | C4: P001 | E4: 50 | H4: S001
A5: IN002 | B5: 46178 | C5: P002 | E5: 20 | H5: S001
D6: =IFERROR(VLOOKUP(C6,①商品マスタ!$A$4:$I$106,2,0),"") | F6: =IFERROR(VLOOKUP(C6,①商品マスタ!$A$4:$I$106,4,0),"") | G6: =IFERROR(IF(AND(E6<>"",F6<>""),E6*F6,""),"") | I6: =IFERROR(VLOOKUP(H6,②仕入先マスタ!$A$4:$G$55,2,0),"")
D7: =IFERROR(VLOOKUP(C7,①商品マスタ!$A$4:$I$106,2,0),"") | F7: =IFERROR(VLOOKUP(C7,①商品マスタ!$A$4:$I$106,4,0),"") | G7: =IFERROR(IF(AND(E7<>"",F7<>""),E7*F7,""),"") | I7: =IFERROR(VLOOKUP(H7,②仕入先マスタ!$A$4:$G$55,2,0),"")
D8: =IFERROR(VLOOKUP(C8,①商品マスタ!$A$4:$I$106,2,0),"") | F8: =IFERROR(VLOOKUP(C8,①商品マスタ!$A$4:$I$106,4,0),"") | G8: =IFERROR(IF(AND(E8<>"",F8<>""),E8*F8,""),"") | I8: =IFERROR(VLOOKUP(H8,②仕入先マスタ!$A$4:$G$55,2,0),"")
D9: =IFERROR(VLOOKUP(C9,①商品マスタ!$A$4:$I$106,2,0),"") | F9: =IFERROR(VLOOKUP(C9,①商品マスタ!$A$4:$I$106,4,0),"") | G9: =IFERROR(IF(AND(E9<>"",F9<>""),E9*F9,""),"") | I9: =IFERROR(VLOOKUP(H9,②仕入先マスタ!$A$4:$G$55,2,0),"")
D10: =IFERROR(VLOOKUP(C10,①商品マスタ!$A$4:$I$106,2,0),"") | F10: =IFERROR(VLOOKUP(C10,①商品マスタ!$A$4:$I$106,4,0),"") | G10: =IFERROR(IF(AND(E10<>"",F10<>""),E10*F10,""),"") | I10: =IFERROR(VLOOKUP(H10,②仕入先マスタ!$A$4:$G$55,2,0),"")
D11: =IFERROR(VLOOKUP(C11,①商品マスタ!$A$4:$I$106,2,0),"") | F11: =IFERROR(VLOOKUP(C11,①商品マスタ!$A$4:$I$106,4,0),"") | G11: =IFERROR(IF(AND(E11<>"",F11<>""),E11*F11,""),"") | I11: =IFERROR(VLOOKUP(H11,②仕入先マスタ!$A$4:$G$55,2,0),"")
D12: =IFERROR(VLOOKUP(C12,①商品マスタ!$A$4:$I$106,2,0),"") | F12: =IFERROR(VLOOKUP(C12,①商品マスタ!$A$4:$I$106,4,0),"") | G12: =IFERROR(IF(AND(E12<>"",F12<>""),E12*F12,""),"") | I12: =IFERROR(VLOOKUP(H12,②仕入先マスタ!$A$4:$G$55,2,0),"")
D13: =IFERROR(VLOOKUP(C13,①商品マスタ!$A$4:$I$106,2,0),"") | F13: =IFERROR(VLOOKUP(C13,①商品マスタ!$A$4:$I$106,4,0),"") | G13: =IFERROR(IF(AND(E13<>"",F13<>""),E13*F13,""),"") | I13: =IFERROR(VLOOKUP(H13,②仕入先マスタ!$A$4:$G$55,2,0),"")
D14: =IFERROR(VLOOKUP(C14,①商品マスタ!$A$4:$I$106,2,0),"") | F14: =IFERROR(VLOOKUP(C14,①商品マスタ!$A$4:$I$106,4,0),"") | G14: =IFERROR(IF(AND(E14<>"",F14<>""),E14*F14,""),"") | I14: =IFERROR(VLOOKUP(H14,②仕入先マスタ!$A$4:$G$55,2,0),"")
D15: =IFERROR(VLOOKUP(C15,①商品マスタ!$A$4:$I$106,2,0),"") | F15: =IFERROR(VLOOKUP(C15,①商品マスタ!$A$4:$I$106,4,0),"") | G15: =IFERROR(IF(AND(E15<>"",F15<>""),E15*F15,""),"") | I15: =IFERROR(VLOOKUP(H15,②仕入先マスタ!$A$4:$G$55,2,0),"")
D16: =IFERROR(VLOOKUP(C16,①商品マスタ!$A$4:$I$106,2,0),"") | F16: =IFERROR(VLOOKUP(C16,①商品マスタ!$A$4:$I$106,4,0),"") | G16: =IFERROR(IF(AND(E16<>"",F16<>""),E16*F16,""),"") | I16: =IFERROR(VLOOKUP(H16,②仕入先マスタ!$A$4:$G$55,2,0),"")
D17: =IFERROR(VLOOKUP(C17,①商品マスタ!$A$4:$I$106,2,0),"") | F17: =IFERROR(VLOOKUP(C17,①商品マスタ!$A$4:$I$106,4,0),"") | G17: =IFERROR(IF(AND(E17<>"",F17<>""),E17*F17,""),"") | I17: =IFERROR(VLOOKUP(H17,②仕入先マスタ!$A$4:$G$55,2,0),"")
... D205: =IFERROR(VLOOKUP(C205,①商品マスタ!$A$4:$I$106,2,0),"") | F205: =IFERROR(VLOOKUP(C205,①商品マスタ!$A$4:$I$106,4,0),"") | G205: =IFERROR(IF(AND(E205<>"",F205<>""),E205*F205,""),"") | I205: =IFERROR(VLOOKUP(H205,②仕入先マスタ!$A$4:$G$55,2,0),"")

Sheet ④出庫管理
A1: ④ 出庫管理 ― 販売・払出しを記録します
A2: ※ 商品IDを入力すると商品名・販売単価が自動表示されます。⑤在庫残高に自動反映されます。
A3: 出庫ID | B3: 出庫日 | C3: 商品ID | D3: 商品名（自動） | E3: 数量 | F3: 販売単価（自動） | G3: 売上金額（自動） | H3: 出庫先・販売先 | I3: 備考
D4: =IFERROR(VLOOKUP(C4,①商品マスタ!$A$4:$I$106,2,0),"") | F4: =IFERROR(VLOOKUP(C4,①商品マスタ!$A$4:$I$106,5,0),"") | G4: =IFERROR(IF(AND(E4<>"",F4<>""),E4*F4,""),"")
D5: =IFERROR(VLOOKUP(C5,①商品マスタ!$A$4:$I$106,2,0),"") | F5: =IFERROR(VLOOKUP(C5,①商品マスタ!$A$4:$I$106,5,0),"") | G5: =IFERROR(IF(AND(E5<>"",F5<>""),E5*F5,""),"")
D6: =IFERROR(VLOOKUP(C6,①商品マスタ!$A$4:$I$106,2,0),"") | F6: =IFERROR(VLOOKUP(C6,①商品マスタ!$A$4:$I$106,5,0),"") | G6: =IFERROR(IF(AND(E6<>"",F6<>""),E6*F6,""),"")
D7: =IFERROR(VLOOKUP(C7,①商品マスタ!$A$4:$I$106,2,0),"") | F7: =IFERROR(VLOOKUP(C7,①商品マスタ!$A$4:$I$106,5,0),"") | G7: =IFERROR(IF(AND(E7<>"",F7<>""),E7*F7,""),"")
D8: =IFERROR(VLOOKUP(C8,①商品マスタ!$A$4:$I$106,2,0),"") | F8: =IFERROR(VLOOKUP(C8,①商品マスタ!$A$4:$I$106,5,0),"") | G8: =IFERROR(IF(AND(E8<>"",F8<>""),E8*F8,""),"")
D9: =IFERROR(VLOOKUP(C9,①商品マスタ!$A$4:$I$106,2,0),"") | F9: =IFERROR(VLOOKUP(C9,①商品マスタ!$A$4:$I$106,5,0),"") | G9: =IFERROR(IF(AND(E9<>"",F9<>""),E9*F9,""),"")
D10: =IFERROR(VLOOKUP(C10,①商品マスタ!$A$4:$I$106,2,0),"") | F10: =IFERROR(VLOOKUP(C10,①商品マスタ!$A$4:$I$106,5,0),"") | G10: =IFERROR(IF(AND(E10<>"",F10<>""),E10*F10,""),"")
D11: =IFERROR(VLOOKUP(C11,①商品マスタ!$A$4:$I$106,2,0),"") | F11: =IFERROR(VLOOKUP(C11,①商品マスタ!$A$4:$I$106,5,0),"") | G11: =IFERROR(IF(AND(E11<>"",F11<>""),E11*F11,""),"")
D12: =IFERROR(VLOOKUP(C12,①商品マスタ!$A$4:$I$106,2,0),"") | F12: =IFERROR(VLOOKUP(C12,①商品マスタ!$A$4:$I$106,5,0),"") | G12: =IFERROR(IF(AND(E12<>"",F12<>""),E12*F12,""),"")
D13: =IFERROR(VLOOKUP(C13,①商品マスタ!$A$4:$I$106,2,0),"") | F13: =IFERROR(VLOOKUP(C13,①商品マスタ!$A$4:$I$106,5,0),"") | G13: =IFERROR(IF(AND(E13<>"",F13<>""),E13*F13,""),"")
D14: =IFERROR(VLOOKUP(C14,①商品マスタ!$A$4:$I$106,2,0),"") | F14: =IFERROR(VLOOKUP(C14,①商品マスタ!$A$4:$I$106,5,0),"") | G14: =IFERROR(IF(AND(E14<>"",F14<>""),E14*F14,""),"")
D15: =IFERROR(VLOOKUP(C15,①商品マスタ!$A$4:$I$106,2,0),"") | F15: =IFERROR(VLOOKUP(C15,①商品マスタ!$A$4:$I$106,5,0),"") | G15: =IFERROR(IF(AND(E15<>"",F15<>""),E15*F15,""),"")
... D203: =IFERROR(VLOOKUP(C203,①商品マスタ!$A$4:$I$106,2,0),"") | F203: =IFERROR(VLOOKUP(C203,①商品マスタ!$A$4:$I$106,5,0),"") | G203: =IFERROR(IF(AND(E203<>"",F203<>""),E203*F203,""),"")

Sheet ⑤在庫残高
A1: ⑤ 在庫残高 ― 入庫－出庫の現在庫数を自動計算します
A2: ※「在庫管理＝管理する」の商品のみアラート対象です。最低在庫数を下回ると赤くハイライトされます。
A3: 商品ID（自動） | B3: 商品名（自動） | C3: 在庫管理 | D3: 最低在庫数 | E3: 入庫合計（自動） | F3: 出庫合計（自動） | G3: 現在庫数（自動） | H3: 状態（自動） | I3: 備考
A4: =IFERROR(①商品マスタ!A4,"") -> P001 | B4: =IFERROR(①商品マスタ!B4,"") -> 商品A | C4: =IFERROR(①商品マスタ!H4,"") -> 管理する | D4: =IFERROR(①商品マスタ!G4,"") -> 10 | E4: =IFERROR(SUMIF(③入庫管理!$C$4:$C$205,A4,③入庫管理!$E$4:$E$205),0) -> 50 | F4: =IFERROR(SUMIF(④出庫管理!$C$4:$C$203,A4,④出庫管理!$E$4:$E$203),0) -> 0 | G4: =IFERROR(IF(A4="","",E4-F4),"") -> 50 | H4: =IFERROR(IF(A4="","",IF(C4="管理しない","対象外",IF(G4<=0,"⚠ 在庫なし",IF(G4<=D4,"⚠ 要発注","OK")))),"") -> OK
A5: =IFERROR(①商品マスタ!A5,"") -> P002 | B5: =IFERROR(①商品マスタ!B5,"") -> 商品B | C5: =IFERROR(①商品マスタ!H5,"") -> 管理する | D5: =IFERROR(①商品マスタ!G5,"") -> 5 | E5: =IFERROR(SUMIF(③入庫管理!$C$4:$C$205,A5,③入庫管理!$E$4:$E$205),0) -> 20 | F5: =IFERROR(SUMIF(④出庫管理!$C$4:$C$203,A5,④出庫管理!$E$4:$E$203),0) -> 0 | G5: =IFERROR(IF(A5="","",E5-F5),"") -> 20 | H5: =IFERROR(IF(A5="","",IF(C5="管理しない","対象外",IF(G5<=0,"⚠ 在庫なし",IF(G5<=D5,"⚠ 要発注","OK")))),"") -> OK
A6: =IFERROR(①商品マスタ!A6,"") -> P003 | B6: =IFERROR(①商品マスタ!B6,"") -> 商品C | C6: =IFERROR(①商品マスタ!H6,"") -> 管理しない | D6: =IFERROR(①商品マスタ!G6,"") -> 0 | E6: =IFERROR(SUMIF(③入庫管理!$C$4:$C$205,A6,③入庫管理!$E$4:$E$205),0) -> 0 | F6: =IFERROR(SUMIF(④出庫管理!$C$4:$C$203,A6,④出庫管理!$E$4:$E$203),0) -> 0 | G6: =IFERROR(IF(A6="","",E6-F6),"") -> 0 | H6: =IFERROR(IF(A6="","",IF(C6="管理しない","対象外",IF(G6<=0,"⚠ 在庫なし",IF(G6<=D6,"⚠ 要発注","OK")))),"") -> 対象外
A7: =IFERROR(①商品マスタ!A7,"") -> 0 | B7: =IFERROR(①商品マスタ!B7,"") -> 0 | C7: =IFERROR(①商品マスタ!H7,"") -> 管理する | D7: =IFERROR(①商品マスタ!G7,"") -> 0 | E7: =IFERROR(SUMIF(③入庫管理!$C$4:$C$205,A7,③入庫管理!$E$4:$E$205),0) -> 0 | F7: =IFERROR(SUMIF(④出庫管理!$C$4:$C$203,A7,④出庫管理!$E$4:$E$203),0) -> 0 | G7: =IFERROR(IF(A7="","",E7-F7),"") -> 0 | H7: =IFERROR(IF(A7="","",IF(C7="管理しない","対象外",IF(G7<=0,"⚠ 在庫なし",IF(G7<=D7,"⚠ 要発注","OK")))),"") -> ⚠ 在庫なし
A8: =IFERROR(①商品マスタ!A8,"") -> 0 | B8: =IFERROR(①商品マスタ!B8,"") -> 0 | C8: =IFERROR(①商品マスタ!H8,"") -> 管理する | D8: =IFERROR(①商品マスタ!G8,"") -> 0 | E8: =IFERROR(SUMIF(③入庫管理!$C$4:$C$205,A8,③入庫管理!$E$4:$E$205),0) -> 0 | F8: =IFERROR(SUMIF(④出庫管理!$C$4:$C$203,A8,④出庫管理!$E$4:$E$203),0) -> 0 | G8: =IFERROR(IF(A8="","",E8-F8),"") -> 0 | H8: =IFERROR(IF(A8="","",IF(C8="管理しない","対象外",IF(G8<=0,"⚠ 在庫なし",IF(G8<=D8,"⚠ 要発注","OK")))),"") -> ⚠ 在庫なし
A9: =IFERROR(①商品マスタ!A9,"") -> 0 | B9: =IFERROR(①商品マスタ!B9,"") -> 0 | C9: =IFERROR(①商品マスタ!H9,"") -> 管理する | D9: =IFERROR(①商品マスタ!G9,"") -> 0 | E9: =IFERROR(SUMIF(③入庫管理!$C$4:$C$205,A9,③入庫管理!$E$4:$E$205),0) -> 0 | F9: =IFERROR(SUMIF(④出庫管理!$C$4:$C$203,A9,④出庫管理!$E$4:$E$203),0) -> 0 | G9: =IFERROR(IF(A9="","",E9-F9),"") -> 0 | H9: =IFERROR(IF(A9="","",IF(C9="管理しない","対象外",IF(G9<=0,"⚠ 在庫なし",IF(G9<=D9,"⚠ 要発注","OK")))),"") -> ⚠ 在庫なし
A10: =IFERROR(①商品マスタ!A10,"") -> 0 | B10: =IFERROR(①商品マスタ!B10,"") -> 0 | C10: =IFERROR(①商品マスタ!H10,"") -> 管理する | D10: =IFERROR(①商品マスタ!G10,"") -> 0 | E10: =IFERROR(SUMIF(③入庫管理!$C$4:$C$205,A10,③入庫管理!$E$4:$E$205),0) -> 0 | F10: =IFERROR(SUMIF(④出庫管理!$C$4:$C$203,A10,④出庫管理!$E$4:$E$203),0) -> 0 | G10: =IFERROR(IF(A10="","",E10-F10),"") -> 0 | H10: =IFERROR(IF(A10="","",IF(C10="管理しない","対象外",IF(G10<=0,"⚠ 在庫なし",IF(G10<=D10,"⚠ 要発注","OK")))),"") -> ⚠ 在庫なし
A11: =IFERROR(①商品マスタ!A11,"") -> 0 | B11: =IFERROR(①商品マスタ!B11,"") -> 0 | C11: =IFERROR(①商品マスタ!H11,"") -> 管理する | D11: =IFERROR(①商品マスタ!G11,"") -> 0 | E11: =IFERROR(SUMIF(③入庫管理!$C$4:$C$205,A11,③入庫管理!$E$4:$E$205),0) -> 0 | F11: =IFERROR(SUMIF(④出庫管理!$C$4:$C$203,A11,④出庫管理!$E$4:$E$203),0) -> 0 | G11: =IFERROR(IF(A11="","",E11-F11),"") -> 0 | H11: =IFERROR(IF(A11="","",IF(C11="管理しない","対象外",IF(G11<=0,"⚠ 在庫なし",IF(G11<=D11,"⚠ 要発注","OK")))),"") -> ⚠ 在庫なし
A12: =IFERROR(①商品マスタ!A12,"") -> 0 | B12: =IFERROR(①商品マスタ!B12,"") -> 0 | C12: =IFERROR(①商品マスタ!H12,"") -> 管理する | D12: =IFERROR(①商品マスタ!G12,"") -> 0 | E12: =IFERROR(SUMIF(③入庫管理!$C$4:$C$205,A12,③入庫管理!$E$4:$E$205),0) -> 0 | F12: =IFERROR(SUMIF(④出庫管理!$C$4:$C$203,A12,④出庫管理!$E$4:$E$203),0) -> 0 | G12: =IFERROR(IF(A12="","",E12-F12),"") -> 0 | H12: =IFERROR(IF(A12="","",IF(C12="管理しない","対象外",IF(G12<=0,"⚠ 在庫なし",IF(G12<=D12,"⚠ 要発注","OK")))),"") -> ⚠ 在庫なし
A13: =IFERROR(①商品マスタ!A13,"") -> 0 | B13: =IFERROR(①商品マスタ!B13,"") -> 0 | C13: =IFERROR(①商品マスタ!H13,"") -> 管理する | D13: =IFERROR(①商品マスタ!G13,"") -> 0 | E13: =IFERROR(SUMIF(③入庫管理!$C$4:$C$205,A13,③入庫管理!$E$4:$E$205),0) -> 0 | F13: =IFERROR(SUMIF(④出庫管理!$C$4:$C$203,A13,④出庫管理!$E$4:$E$203),0) -> 0 | G13: =IFERROR(IF(A13="","",E13-F13),"") -> 0 | H13: =IFERROR(IF(A13="","",IF(C13="管理しない","対象外",IF(G13<=0,"⚠ 在庫なし",IF(G13<=D13,"⚠ 要発注","OK")))),"") -> ⚠ 在庫なし
A14: =IFERROR(①商品マスタ!A14,"") -> 0 | B14: =IFERROR(①商品マスタ!B14,"") -> 0 | C14: =IFERROR(①商品マスタ!H14,"") -> 管理する | D14: =IFERROR(①商品マスタ!G14,"") -> 0 | E14: =IFERROR(SUMIF(③入庫管理!$C$4:$C$205,A14,③入庫管理!$E$4:$E$205),0) -> 0 | F14: =IFERROR(SUMIF(④出庫管理!$C$4:$C$203,A14,④出庫管理!$E$4:$E$203),0) -> 0 | G14: =IFERROR(IF(A14="","",E14-F14),"") -> 0 | H14: =IFERROR(IF(A14="","",IF(C14="管理しない","対象外",IF(G14<=0,"⚠ 在庫なし",IF(G14<=D14,"⚠ 要発注","OK")))),"") -> ⚠ 在庫なし
A15: =IFERROR(①商品マスタ!A15,"") -> 0 | B15: =IFERROR(①商品マスタ!B15,"") -> 0 | C15: =IFERROR(①商品マスタ!H15,"") -> 管理する | D15: =IFERROR(①商品マスタ!G15,"") -> 0 | E15: =IFERROR(SUMIF(③入庫管理!$C$4:$C$205,A15,③入庫管理!$E$4:$E$205),0) -> 0 | F15: =IFERROR(SUMIF(④出庫管理!$C$4:$C$203,A15,④出庫管理!$E$4:$E$203),0) -> 0 | G15: =IFERROR(IF(A15="","",E15-F15),"") -> 0 | H15: =IFERROR(IF(A15="","",IF(C15="管理しない","対象外",IF(G15<=0,"⚠ 在庫なし",IF(G15<=D15,"⚠ 要発注","OK")))),"") -> ⚠ 在庫なし
... A106: =IFERROR(①商品マスタ!A106,"") -> 0 | B106: =IFERROR(①商品マスタ!B106,"") -> 0 | C106: =IFERROR(①商品マスタ!H106,"") -> 管理する | D106: =IFERROR(①商品マスタ!G106,"") -> 0 | E106: =IFERROR(SUMIF(③入庫管理!$C$4:$C$205,A106,③入庫管理!$E$4:$E$205),0) -> 0 | F106: =IFERROR(SUMIF(④出庫管理!$C$4:$C$203,A106,④出庫管理!$E$4:$E$203),0) -> 0 | G106: =IFERROR(IF(A106="","",E106-F106),"") -> 0 | H106: =IFERROR(IF(A106="","",IF(C106="管理しない","対象外",IF(G106<=0,"⚠ 在庫なし",IF(G106<=D106,"⚠ 要発注","OK")))),"") -> ⚠ 在庫なし

Sheet ⑥棚卸しシート
A1: ⑥ 棚卸しシート ― 定期的な実在庫の確認と差異チェックをします
A2: ※ 棚卸し日と担当者を入力し、実在庫数を記入してください。帳簿在庫（⑤自動参照）との差異が自動計算されます。
A3: 棚卸し日 | C3: 担当者
A4: 商品ID（自動） | B4: 商品名（自動） | C4: 帳簿在庫（自動） | D4: 実在庫数（入力） | E4: 差異（自動） | F4: 差異コメント | G4: 確認済
A5: =IFERROR(⑤在庫残高!A4,"") -> P001 | B5: =IFERROR(⑤在庫残高!B4,"") -> 商品A | C5: =IFERROR(⑤在庫残高!G4,"") -> 50 | E5: =IFERROR(IF(AND(C5<>"",D5<>""),D5-C5,""),"")
A6: =IFERROR(⑤在庫残高!A5,"") -> P002 | B6: =IFERROR(⑤在庫残高!B5,"") -> 商品B | C6: =IFERROR(⑤在庫残高!G5,"") -> 20 | E6: =IFERROR(IF(AND(C6<>"",D6<>""),D6-C6,""),"")
A7: =IFERROR(⑤在庫残高!A6,"") -> P003 | B7: =IFERROR(⑤在庫残高!B6,"") -> 商品C | C7: =IFERROR(⑤在庫残高!G6,"") -> 0 | E7: =IFERROR(IF(AND(C7<>"",D7<>""),D7-C7,""),"")
A8: =IFERROR(⑤在庫残高!A7,"") -> 0 | B8: =IFERROR(⑤在庫残高!B7,"") -> 0 | C8: =IFERROR(⑤在庫残高!G7,"") -> 0 | E8: =IFERROR(IF(AND(C8<>"",D8<>""),D8-C8,""),"")
A9: =IFERROR(⑤在庫残高!A8,"") -> 0 | B9: =IFERROR(⑤在庫残高!B8,"") -> 0 | C9: =IFERROR(⑤在庫残高!G8,"") -> 0 | E9: =IFERROR(IF(AND(C9<>"",D9<>""),D9-C9,""),"")
A10: =IFERROR(⑤在庫残高!A9,"") -> 0 | B10: =IFERROR(⑤在庫残高!B9,"") -> 0 | C10: =IFERROR(⑤在庫残高!G9,"") -> 0 | E10: =IFERROR(IF(AND(C10<>"",D10<>""),D10-C10,""),"")
A11: =IFERROR(⑤在庫残高!A10,"") -> 0 | B11: =IFERROR(⑤在庫残高!B10,"") -> 0 | C11: =IFERROR(⑤在庫残高!G10,"") -> 0 | E11: =IFERROR(IF(AND(C11<>"",D11<>""),D11-C11,""),"")
A12: =IFERROR(⑤在庫残高!A11,"") -> 0 | B12: =IFERROR(⑤在庫残高!B11,"") -> 0 | C12: =IFERROR(⑤在庫残高!G11,"") -> 0 | E12: =IFERROR(IF(AND(C12<>"",D12<>""),D12-C12,""),"")
A13: =IFERROR(⑤在庫残高!A12,"") -> 0 | B13: =IFERROR(⑤在庫残高!B12,"") -> 0 | C13: =IFERROR(⑤在庫残高!G12,"") -> 0 | E13: =IFERROR(IF(AND(C13<>"",D13<>""),D13-C13,""),"")
A14: =IFERROR(⑤在庫残高!A13,"") -> 0 | B14: =IFERROR(⑤在庫残高!B13,"") -> 0 | C14: =IFERROR(⑤在庫残高!G13,"") -> 0 | E14: =IFERROR(IF(AND(C14<>"",D14<>""),D14-C14,""),"")
A15: =IFERROR(⑤在庫残高!A14,"") -> 0 | B15: =IFERROR(⑤在庫残高!B14,"") -> 0 | C15: =IFERROR(⑤在庫残高!G14,"") -> 0 | E15: =IFERROR(IF(AND(C15<>"",D15<>""),D15-C15,""),"")
A16: =IFERROR(⑤在庫残高!A15,"") -> 0 | B16: =IFERROR(⑤在庫残高!B15,"") -> 0 | C16: =IFERROR(⑤在庫残高!G15,"") -> 0 | E16: =IFERROR(IF(AND(C16<>"",D16<>""),D16-C16,""),"")
... A107: =IFERROR(⑤在庫残高!A106,"") -> 0 | B107: =IFERROR(⑤在庫残高!B106,"") -> 0 | C107: =IFERROR(⑤在庫残高!G106,"") -> 0 | E107: =IFERROR(IF(AND(C107<>"",D107<>""),D107-C107,""),"")
